{
"meta":{"test_sets":[],"test_metrics":[],"learn_metrics":[{"best_value":"Min","name":"Logloss"}],"launch_mode":"Train","parameters":"","iteration_count":1000,"learn_sets":["learn"],"name":"experiment"},
"iterations":[
{"learn":[0.6602254088],"iteration":0,"passed_time":0.00887268734,"remaining_time":8.863814653},
{"learn":[0.6331419761],"iteration":1,"passed_time":0.01734684057,"remaining_time":8.656073443},
{"learn":[0.6059262446],"iteration":2,"passed_time":0.02508889268,"remaining_time":8.337875335},
{"learn":[0.5850694427],"iteration":3,"passed_time":0.03294883263,"remaining_time":8.204259324},
{"learn":[0.5665337581],"iteration":4,"passed_time":0.04070088534,"remaining_time":8.099476183},
{"learn":[0.5491356097],"iteration":5,"passed_time":0.04910885624,"remaining_time":8.135700517},
{"learn":[0.5321182904],"iteration":6,"passed_time":0.05927920074,"remaining_time":8.409178047},
{"learn":[0.5182033878],"iteration":7,"passed_time":0.06763326762,"remaining_time":8.386525184},
{"learn":[0.5042797352],"iteration":8,"passed_time":0.07706597967,"remaining_time":8.48582065},
{"learn":[0.4912526122],"iteration":9,"passed_time":0.08688988017,"remaining_time":8.602098137},
{"learn":[0.4797575284],"iteration":10,"passed_time":0.09587132884,"remaining_time":8.619704021},
{"learn":[0.4680249674],"iteration":11,"passed_time":0.1043516569,"remaining_time":8.591619751},
{"learn":[0.4576996296],"iteration":12,"passed_time":0.1128162076,"remaining_time":8.565353611},
{"learn":[0.4473685448],"iteration":13,"passed_time":0.1215904097,"remaining_time":8.563438852},
{"learn":[0.4395900362],"iteration":14,"passed_time":0.1306375708,"remaining_time":8.578533813},
{"learn":[0.4318291006],"iteration":15,"passed_time":0.1396217566,"remaining_time":8.586738031},
{"learn":[0.4250578638],"iteration":16,"passed_time":0.1477450679,"remaining_time":8.54314128},
{"learn":[0.419237311],"iteration":17,"passed_time":0.1555838411,"remaining_time":8.487962884},
{"learn":[0.4127413217],"iteration":18,"passed_time":0.1637751064,"remaining_time":8.455967336},
{"learn":[0.4076341268],"iteration":19,"passed_time":0.172136867,"remaining_time":8.434706484},
{"learn":[0.4034111528],"iteration":20,"passed_time":0.1805148518,"remaining_time":8.415430472},
{"learn":[0.3980483171],"iteration":21,"passed_time":0.1885921921,"remaining_time":8.383780178},
{"learn":[0.3942767477],"iteration":22,"passed_time":0.1964295103,"remaining_time":8.343983982},
{"learn":[0.3901477925],"iteration":23,"passed_time":0.2045924351,"remaining_time":8.320092359},
{"learn":[0.3862268765],"iteration":24,"passed_time":0.2129227803,"remaining_time":8.303988431},
{"learn":[0.3818869644],"iteration":25,"passed_time":0.222232473,"remaining_time":8.325170335},
{"learn":[0.3783291978],"iteration":26,"passed_time":0.2305135814,"remaining_time":8.307026472},
{"learn":[0.3756776597],"iteration":27,"passed_time":0.2390920376,"remaining_time":8.299909306},
{"learn":[0.3728682653],"iteration":28,"passed_time":0.2475959699,"remaining_time":8.290196094},
{"learn":[0.3706904234],"iteration":29,"passed_time":0.2557392937,"remaining_time":8.268903829},
{"learn":[0.367948294],"iteration":30,"passed_time":0.2636061181,"remaining_time":8.239817046},
{"learn":[0.3665042558],"iteration":31,"passed_time":0.271395235,"remaining_time":8.209705859},
{"learn":[0.3644329206],"iteration":32,"passed_time":0.2795823374,"remaining_time":8.192609705},
{"learn":[0.3624159083],"iteration":33,"passed_time":0.2889228973,"remaining_time":8.208809378},
{"learn":[0.3608377408],"iteration":34,"passed_time":0.2986377816,"remaining_time":8.233870263},
{"learn":[0.3593271495],"iteration":35,"passed_time":0.3078716425,"remaining_time":8.244118427},
{"learn":[0.3577456908],"iteration":36,"passed_time":0.3172815936,"remaining_time":8.257896611},
{"learn":[0.3567350918],"iteration":37,"passed_time":0.3259222806,"remaining_time":8.250979839},
{"learn":[0.3550090622],"iteration":38,"passed_time":0.3350923356,"remaining_time":8.257018835},
{"learn":[0.3538600366],"iteration":39,"passed_time":0.3437401512,"remaining_time":8.249763628},
{"learn":[0.3525178778],"iteration":40,"passed_time":0.3521651747,"remaining_time":8.237229329},
{"learn":[0.3510674516],"iteration":41,"passed_time":0.3601610883,"remaining_time":8.21510292},
{"learn":[0.3497785565],"iteration":42,"passed_time":0.3680865749,"remaining_time":8.192066331},
{"learn":[0.3490868572],"iteration":43,"passed_time":0.3761027913,"remaining_time":8.171687921},
{"learn":[0.3480886111],"iteration":44,"passed_time":0.3840355379,"remaining_time":8.150087526},
{"learn":[0.3470999835],"iteration":45,"passed_time":0.392461278,"remaining_time":8.139305634},
{"learn":[0.3458340053],"iteration":46,"passed_time":0.4003890196,"remaining_time":8.118526292},
{"learn":[0.3447597731],"iteration":47,"passed_time":0.408343737,"remaining_time":8.098817451},
{"learn":[0.3436645372],"iteration":48,"passed_time":0.4162441354,"remaining_time":8.078534137},
{"learn":[0.3427635764],"iteration":49,"passed_time":0.4244176272,"remaining_time":8.063934916},
{"learn":[0.3420573671],"iteration":50,"passed_time":0.432129269,"remaining_time":8.040993652},
{"learn":[0.3413208755],"iteration":51,"passed_time":0.4407600389,"remaining_time":8.035394555},
{"learn":[0.3405455503],"iteration":52,"passed_time":0.448594981,"remaining_time":8.015461265},
{"learn":[0.3396571366],"iteration":53,"passed_time":0.4564720153,"remaining_time":7.996713453},
{"learn":[0.3389223057],"iteration":54,"passed_time":0.4648170701,"remaining_time":7.986402387},
{"learn":[0.3384092255],"iteration":55,"passed_time":0.473072609,"remaining_time":7.974652553},
{"learn":[0.3377030671],"iteration":56,"passed_time":0.4811892339,"remaining_time":7.96072715},
{"learn":[0.3371212079],"iteration":57,"passed_time":0.4891452009,"remaining_time":7.944392745},
{"learn":[0.3367664388],"iteration":58,"passed_time":0.4976241266,"remaining_time":7.936683104},
{"learn":[0.3362732283],"iteration":59,"passed_time":0.5065008638,"remaining_time":7.9351802},
{"learn":[0.3358961644],"iteration":60,"passed_time":0.5150815181,"remaining_time":7.928877794},
{"learn":[0.3353901092],"iteration":61,"passed_time":0.5232252426,"remaining_time":7.915891574},
{"learn":[0.3347609982],"iteration":62,"passed_time":0.5312019705,"remaining_time":7.900575338},
{"learn":[0.3342321765],"iteration":63,"passed_time":0.5392226061,"remaining_time":7.886130614},
{"learn":[0.3337475542],"iteration":64,"passed_time":0.5479953001,"remaining_time":7.882701624},
{"learn":[0.333173372],"iteration":65,"passed_time":0.5558587686,"remaining_time":7.866243786},
{"learn":[0.3327222762],"iteration":66,"passed_time":0.5638180628,"remaining_time":7.851376904},
{"learn":[0.3325208081],"iteration":67,"passed_time":0.571764479,"remaining_time":7.836536683},
{"learn":[0.3321944038],"iteration":68,"passed_time":0.5804142851,"remaining_time":7.831386949},
{"learn":[0.3318521098],"iteration":69,"passed_time":0.5901382571,"remaining_time":7.840408273},
{"learn":[0.3314062909],"iteration":70,"passed_time":0.5991955023,"remaining_time":7.84017777},
{"learn":[0.3311033129],"iteration":71,"passed_time":0.6076911578,"remaining_time":7.832463812},
{"learn":[0.3308104148],"iteration":72,"passed_time":0.6157165138,"remaining_time":7.818756278},
{"learn":[0.3305086986],"iteration":73,"passed_time":0.6237213338,"remaining_time":7.804945339},
{"learn":[0.3301610974],"iteration":74,"passed_time":0.6316044498,"remaining_time":7.789788214},
{"learn":[0.3297657232],"iteration":75,"passed_time":0.6398447092,"remaining_time":7.779164622},
{"learn":[0.3292088589],"iteration":76,"passed_time":0.6481041361,"remaining_time":7.768832696},
{"learn":[0.3289192392],"iteration":77,"passed_time":0.6562227358,"remaining_time":7.756889261},
{"learn":[0.3286302172],"iteration":78,"passed_time":0.6642379258,"remaining_time":7.743837084},
{"learn":[0.3282830658],"iteration":79,"passed_time":0.6722769528,"remaining_time":7.731184957},
{"learn":[0.3277810467],"iteration":80,"passed_time":0.6800453654,"remaining_time":7.715576429},
{"learn":[0.3274433354],"iteration":81,"passed_time":0.6879306677,"remaining_time":7.701467719},
{"learn":[0.3271015559],"iteration":82,"passed_time":0.6961337371,"remaining_time":7.691019722},
{"learn":[0.3268017558],"iteration":83,"passed_time":0.7044971293,"remaining_time":7.682373458},
{"learn":[0.326631178],"iteration":84,"passed_time":0.7126124493,"remaining_time":7.671063425},
{"learn":[0.3263673237],"iteration":85,"passed_time":0.7205923386,"remaining_time":7.658388342},
{"learn":[0.3261497748],"iteration":86,"passed_time":0.7284089516,"remaining_time":7.644107733},
{"learn":[0.3259100268],"iteration":87,"passed_time":0.7370742909,"remaining_time":7.638769924},
{"learn":[0.3257493099],"iteration":88,"passed_time":0.7453396002,"remaining_time":7.62926265},
{"learn":[0.3256043278],"iteration":89,"passed_time":0.7537443236,"remaining_time":7.621192605},
{"learn":[0.3253928065],"iteration":90,"passed_time":0.7616464588,"remaining_time":7.608094847},
{"learn":[0.3248457332],"iteration":91,"passed_time":0.7693203863,"remaining_time":7.592857726},
{"learn":[0.3246339305],"iteration":92,"passed_time":0.7771652817,"remaining_time":7.57945065},
{"learn":[0.324388223],"iteration":93,"passed_time":0.7852003184,"remaining_time":7.567994558},
{"learn":[0.3242284761],"iteration":94,"passed_time":0.7935004356,"remaining_time":7.559135729},
{"learn":[0.3240424589],"iteration":95,"passed_time":0.8012985285,"remaining_time":7.545561143},
{"learn":[0.3238001226],"iteration":96,"passed_time":0.8094856913,"remaining_time":7.535727621},
{"learn":[0.3236372152],"iteration":97,"passed_time":0.8179523779,"remaining_time":7.528500458},
{"learn":[0.3234011857],"iteration":98,"passed_time":0.8266227387,"remaining_time":7.523101894},
{"learn":[0.3231371577],"iteration":99,"passed_time":0.8351806354,"remaining_time":7.516625719},
{"learn":[0.3229769349],"iteration":100,"passed_time":0.8439814855,"remaining_time":7.512270846},
{"learn":[0.3227208715],"iteration":101,"passed_time":0.8526876848,"remaining_time":7.506995499},
{"learn":[0.3226108848],"iteration":102,"passed_time":0.8614059896,"remaining_time":7.501758958},
{"learn":[0.322537757],"iteration":103,"passed_time":0.8688048026,"remaining_time":7.485087531},
{"learn":[0.3222999431],"iteration":104,"passed_time":0.877481316,"remaining_time":7.479483598},
{"learn":[0.3221910411],"iteration":105,"passed_time":0.8855462536,"remaining_time":7.468663686},
{"learn":[0.3220183883],"iteration":106,"passed_time":0.8936276647,"remaining_time":7.458032753},
{"learn":[0.3217111088],"iteration":107,"passed_time":0.9017217739,"remaining_time":7.44755391},
{"learn":[0.3214255394],"iteration":108,"passed_time":0.9096312413,"remaining_time":7.435609504},
{"learn":[0.3212120323],"iteration":109,"passed_time":0.9175953423,"remaining_time":7.424180497},
{"learn":[0.3210347211],"iteration":110,"passed_time":0.9260607197,"remaining_time":7.416828647},
{"learn":[0.3208640658],"iteration":111,"passed_time":0.9336964362,"remaining_time":7.402878887},
{"learn":[0.320616653],"iteration":112,"passed_time":0.9417934087,"remaining_time":7.392661536},
{"learn":[0.320469652],"iteration":113,"passed_time":0.9501853578,"remaining_time":7.384773921},
{"learn":[0.3202378136],"iteration":114,"passed_time":0.9582485137,"remaining_time":7.374347258},
{"learn":[0.3199611168],"iteration":115,"passed_time":0.9662086902,"remaining_time":7.36317657},
{"learn":[0.3197819473],"iteration":116,"passed_time":0.9742883082,"remaining_time":7.35296219},
{"learn":[0.3196415464],"iteration":117,"passed_time":0.9819861689,"remaining_time":7.339930517},
{"learn":[0.3195061522],"iteration":118,"passed_time":0.989953856,"remaining_time":7.32898611},
{"learn":[0.3193773213],"iteration":119,"passed_time":0.9980298828,"remaining_time":7.318885807},
{"learn":[0.3191121141],"iteration":120,"passed_time":1.005996377,"remaining_time":7.308023266},
{"learn":[0.3189319479],"iteration":121,"passed_time":1.01378106,"remaining_time":7.295899761},
{"learn":[0.3187345649],"iteration":122,"passed_time":1.022205061,"remaining_time":7.288405192},
{"learn":[0.3186533405],"iteration":123,"passed_time":1.031888826,"remaining_time":7.289795257},
{"learn":[0.3184523376],"iteration":124,"passed_time":1.041098081,"remaining_time":7.287686564},
{"learn":[0.3183590516],"iteration":125,"passed_time":1.05025299,"remaining_time":7.285088198},
{"learn":[0.3181313694],"iteration":126,"passed_time":1.05888571,"remaining_time":7.278797047},
{"learn":[0.3180193657],"iteration":127,"passed_time":1.068944595,"remaining_time":7.282185052},
{"learn":[0.3179546302],"iteration":128,"passed_time":1.077898088,"remaining_time":7.277901043},
{"learn":[0.317875811],"iteration":129,"passed_time":1.086769585,"remaining_time":7.272996453},
{"learn":[0.3178210832],"iteration":130,"passed_time":1.094506851,"remaining_time":7.260507281},
{"learn":[0.3177220467],"iteration":131,"passed_time":1.104696994,"remaining_time":7.264219629},
{"learn":[0.3175974019],"iteration":132,"passed_time":1.115160326,"remaining_time":7.269503777},
{"learn":[0.317457959],"iteration":133,"passed_time":1.123875105,"remaining_time":7.263252547},
{"learn":[0.3173371327],"iteration":134,"passed_time":1.133303909,"remaining_time":7.261539864},
{"learn":[0.3171979614],"iteration":135,"passed_time":1.141834383,"remaining_time":7.254006667},
{"learn":[0.3171217423],"iteration":136,"passed_time":1.150911736,"remaining_time":7.249903856},
{"learn":[0.3170298866],"iteration":137,"passed_time":1.159201433,"remaining_time":7.240808951},
{"learn":[0.3168071585],"iteration":138,"passed_time":1.168407756,"remaining_time":7.237403438},
{"learn":[0.3167201716],"iteration":139,"passed_time":1.177518923,"remaining_time":7.233330528},
{"learn":[0.3166348805],"iteration":140,"passed_time":1.186148592,"remaining_time":7.226252768},
{"learn":[0.3165588873],"iteration":141,"passed_time":1.194937335,"remaining_time":7.220114318},
{"learn":[0.3165119001],"iteration":142,"passed_time":1.203193431,"remaining_time":7.210746648},
{"learn":[0.3164269488],"iteration":143,"passed_time":1.212115499,"remaining_time":7.205353242},
{"learn":[0.3162499849],"iteration":144,"passed_time":1.220676862,"remaining_time":7.197784254},
{"learn":[0.3160775571],"iteration":145,"passed_time":1.228933306,"remaining_time":7.188418103},
{"learn":[0.316006771],"iteration":146,"passed_time":1.237540651,"remaining_time":7.181103234},
{"learn":[0.3159491837],"iteration":147,"passed_time":1.245706859,"remaining_time":7.17123138},
{"learn":[0.3158539821],"iteration":148,"passed_time":1.254527781,"remaining_time":7.165121755},
{"learn":[0.3158317766],"iteration":149,"passed_time":1.261250495,"remaining_time":7.147086139},
{"learn":[0.3157951332],"iteration":150,"passed_time":1.268884134,"remaining_time":7.134322052},
{"learn":[0.3157056398],"iteration":151,"passed_time":1.277356278,"remaining_time":7.126303448},
{"learn":[0.3156459981],"iteration":152,"passed_time":1.285458006,"remaining_time":7.116228308},
{"learn":[0.3155384043],"iteration":153,"passed_time":1.295116098,"remaining_time":7.114728693},
{"learn":[0.3154698043],"iteration":154,"passed_time":1.309559534,"remaining_time":7.139211655},
{"learn":[0.3152936011],"iteration":155,"passed_time":1.320373107,"remaining_time":7.143557066},
{"learn":[0.3152822021],"iteration":156,"passed_time":1.329510864,"remaining_time":7.138711197},
{"learn":[0.315205236],"iteration":157,"passed_time":1.340594866,"remaining_time":7.144182765},
{"learn":[0.3151760019],"iteration":158,"passed_time":1.35363637,"remaining_time":7.159799922},
{"learn":[0.3150928788],"iteration":159,"passed_time":1.365463824,"remaining_time":7.168685074},
{"learn":[0.3149633965],"iteration":160,"passed_time":1.375367384,"remaining_time":7.167287177},
{"learn":[0.3147105747],"iteration":161,"passed_time":1.385105494,"remaining_time":7.16492842},
{"learn":[0.3146124602],"iteration":162,"passed_time":1.395189178,"remaining_time":7.164253631},
{"learn":[0.3145245911],"iteration":163,"passed_time":1.404941726,"remaining_time":7.161776117},
{"learn":[0.3144378756],"iteration":164,"passed_time":1.413774014,"remaining_time":7.154553346},
{"learn":[0.3144226313],"iteration":165,"passed_time":1.420849312,"remaining_time":7.138483895},
{"learn":[0.3144200809],"iteration":166,"passed_time":1.426399087,"remaining_time":7.114912814},
{"learn":[0.3143556867],"iteration":167,"passed_time":1.437007083,"remaining_time":7.116606504},
{"learn":[0.3142900205],"iteration":168,"passed_time":1.445912506,"remaining_time":7.109782795},
{"learn":[0.3142207289],"iteration":169,"passed_time":1.455450877,"remaining_time":7.10602487},
{"learn":[0.3140582434],"iteration":170,"passed_time":1.465430577,"remaining_time":7.10433888},
{"learn":[0.3139701475],"iteration":171,"passed_time":1.474791574,"remaining_time":7.099578043},
{"learn":[0.3137843162],"iteration":172,"passed_time":1.484218471,"remaining_time":7.095079049},
{"learn":[0.3137072496],"iteration":173,"passed_time":1.494963856,"remaining_time":7.096782445},
{"learn":[0.3135967301],"iteration":174,"passed_time":1.503706491,"remaining_time":7.088902028},
{"learn":[0.3134328064],"iteration":175,"passed_time":1.513047742,"remaining_time":7.083814431},
{"learn":[0.3133774606],"iteration":176,"passed_time":1.52237685,"remaining_time":7.078622302},
{"learn":[0.3132760422],"iteration":177,"passed_time":1.530909438,"remaining_time":7.069705383},
{"learn":[0.313273621],"iteration":178,"passed_time":1.536727285,"remaining_time":7.048341346},
{"learn":[0.3131974678],"iteration":179,"passed_time":1.54506729,"remaining_time":7.038639877},
{"learn":[0.3131344452],"iteration":180,"passed_time":1.553349065,"remaining_time":7.028689969},
{"learn":[0.3131071427],"iteration":181,"passed_time":1.560278397,"remaining_time":7.012679828},
{"learn":[0.3129514877],"iteration":182,"passed_time":1.568841876,"remaining_time":7.00406455},
{"learn":[0.3128675647],"iteration":183,"passed_time":1.577535099,"remaining_time":6.99602522},
{"learn":[0.3127321252],"iteration":184,"passed_time":1.585504277,"remaining_time":6.984789113},
{"learn":[0.3126061428],"iteration":185,"passed_time":1.595153828,"remaining_time":6.980942023},
{"learn":[0.3125490448],"iteration":186,"passed_time":1.60368103,"remaining_time":6.972153356},
{"learn":[0.3125040567],"iteration":187,"passed_time":1.61182846,"remaining_time":6.96172718},
{"learn":[0.3124698948],"iteration":188,"passed_time":1.620392323,"remaining_time":6.953112031},
{"learn":[0.3124030802],"iteration":189,"passed_time":1.627626913,"remaining_time":6.938830525},
{"learn":[0.312242941],"iteration":190,"passed_time":1.636536126,"remaining_time":6.931715843},
{"learn":[0.3121702904],"iteration":191,"passed_time":1.644943177,"remaining_time":6.922469203},
{"learn":[0.3119248537],"iteration":192,"passed_time":1.654305496,"remaining_time":6.917225572},
{"learn":[0.3118771584],"iteration":193,"passed_time":1.662769214,"remaining_time":6.908206117},
{"learn":[0.3118275865],"iteration":194,"passed_time":1.671282681,"remaining_time":6.899397733},
{"learn":[0.3117377988],"iteration":195,"passed_time":1.680290947,"remaining_time":6.89262205},
{"learn":[0.311614768],"iteration":196,"passed_time":1.688996325,"remaining_time":6.884589082},
{"learn":[0.3115715536],"iteration":197,"passed_time":1.697765528,"remaining_time":6.876807844},
{"learn":[0.3115246361],"iteration":198,"passed_time":1.707252723,"remaining_time":6.87190669},
{"learn":[0.3114413438],"iteration":199,"passed_time":1.71595568,"remaining_time":6.863822721},
{"learn":[0.3113811918],"iteration":200,"passed_time":1.724011526,"remaining_time":6.853160244},
{"learn":[0.3113467171],"iteration":201,"passed_time":1.733569017,"remaining_time":6.84845582},
{"learn":[0.3112945825],"iteration":202,"passed_time":1.742006779,"remaining_time":6.839307402},
{"learn":[0.3112507437],"iteration":203,"passed_time":1.75046124,"remaining_time":6.830231112},
{"learn":[0.3112047182],"iteration":204,"passed_time":1.759139721,"remaining_time":6.822029651},
{"learn":[0.3111247851],"iteration":205,"passed_time":1.768085375,"remaining_time":6.81485334},
{"learn":[0.3109695971],"iteration":206,"passed_time":1.776483402,"remaining_time":6.805562018},
{"learn":[0.3109049417],"iteration":207,"passed_time":1.784816153,"remaining_time":6.796030735},
{"learn":[0.3108707936],"iteration":208,"passed_time":1.793686456,"remaining_time":6.788545391},
{"learn":[0.3108121697],"iteration":209,"passed_time":1.802049753,"remaining_time":6.779139547},
{"learn":[0.3107079157],"iteration":210,"passed_time":1.810295109,"remaining_time":6.769302563},
{"learn":[0.31066287],"iteration":211,"passed_time":1.818842789,"remaining_time":6.760604331},
{"learn":[0.3106548571],"iteration":212,"passed_time":1.824572365,"remaining_time":6.741495075},
{"learn":[0.3105895438],"iteration":213,"passed_time":1.832720147,"remaining_time":6.731392689},
{"learn":[0.3104194293],"iteration":214,"passed_time":1.841569339,"remaining_time":6.723869448},
{"learn":[0.3103665037],"iteration":215,"passed_time":1.850516948,"remaining_time":6.716691145},
{"learn":[0.3103374418],"iteration":216,"passed_time":1.859295013,"remaining_time":6.70888477},
{"learn":[0.3102190196],"iteration":217,"passed_time":1.867300285,"remaining_time":6.698297351},
{"learn":[0.3101956873],"iteration":218,"passed_time":1.875272122,"remaining_time":6.68761428},
{"learn":[0.3101644916],"iteration":219,"passed_time":1.883499587,"remaining_time":6.677862171},
{"learn":[0.3101154717],"iteration":220,"passed_time":1.891508704,"remaining_time":6.667354209},
{"learn":[0.3100565925],"iteration":221,"passed_time":1.899736793,"remaining_time":6.657636147},
{"learn":[0.3099836018],"iteration":222,"passed_time":1.908066034,"remaining_time":6.648283896},
{"learn":[0.3099435024],"iteration":223,"passed_time":1.916502862,"remaining_time":6.639313485},
{"learn":[0.3099381067],"iteration":224,"passed_time":1.92215333,"remaining_time":6.620750359},
{"learn":[0.3098843728],"iteration":225,"passed_time":1.930684054,"remaining_time":6.612165742},
{"learn":[0.3098380307],"iteration":226,"passed_time":1.938838072,"remaining_time":6.602298809},
{"learn":[0.309806137],"iteration":227,"passed_time":1.946073162,"remaining_time":6.589335443},
{"learn":[0.3097119586],"iteration":228,"passed_time":1.954066181,"remaining_time":6.578973912},
{"learn":[0.3096359969],"iteration":229,"passed_time":1.961922359,"remaining_time":6.568174854},
{"learn":[0.3095872787],"iteration":230,"passed_time":1.96995006,"remaining_time":6.557972278},
{"learn":[0.3094963361],"iteration":231,"passed_time":1.977726202,"remaining_time":6.546955704},
{"learn":[0.3094344663],"iteration":232,"passed_time":1.985818152,"remaining_time":6.537006535},
{"learn":[0.3093772241],"iteration":233,"passed_time":1.993880561,"remaining_time":6.526976537},
{"learn":[0.3092639355],"iteration":234,"passed_time":2.001869209,"remaining_time":6.51672317},
{"learn":[0.3092636628],"iteration":235,"passed_time":2.007032506,"remaining_time":6.497342521},
{"learn":[0.3092261434],"iteration":236,"passed_time":2.016533929,"remaining_time":6.49204805},
{"learn":[0.309116915],"iteration":237,"passed_time":2.024465634,"remaining_time":6.481692491},
{"learn":[0.3090804807],"iteration":238,"passed_time":2.032964226,"remaining_time":6.473162243},
{"learn":[0.3090397996],"iteration":239,"passed_time":2.040783363,"remaining_time":6.462480651},
{"learn":[0.3090035202],"iteration":240,"passed_time":2.048964074,"remaining_time":6.452961544},
{"learn":[0.3089715598],"iteration":241,"passed_time":2.056910155,"remaining_time":6.442718584},
{"learn":[0.3089294564],"iteration":242,"passed_time":2.064873715,"remaining_time":6.432548981},
{"learn":[0.3088770894],"iteration":243,"passed_time":2.073102289,"remaining_time":6.423218566},
{"learn":[0.3088271948],"iteration":244,"passed_time":2.081180941,"remaining_time":6.413435144},
{"learn":[0.3087072614],"iteration":245,"passed_time":2.08934994,"remaining_time":6.403942498},
{"learn":[0.3086488487],"iteration":246,"passed_time":2.097176608,"remaining_time":6.393416947},
{"learn":[0.3086175603],"iteration":247,"passed_time":2.105388545,"remaining_time":6.384081394},
{"learn":[0.308566694],"iteration":248,"passed_time":2.113307291,"remaining_time":6.373870584},
{"learn":[0.3084824659],"iteration":249,"passed_time":2.121716394,"remaining_time":6.365149183},
{"learn":[0.308434541],"iteration":250,"passed_time":2.129821447,"remaining_time":6.355522962},
{"learn":[0.3083974997],"iteration":251,"passed_time":2.137732655,"remaining_time":6.345333436},
{"learn":[0.3082756871],"iteration":252,"passed_time":2.145780136,"remaining_time":6.335564276},
{"learn":[0.3082502929],"iteration":253,"passed_time":2.154417781,"remaining_time":6.327541986},
{"learn":[0.3081457037],"iteration":254,"passed_time":2.162360487,"remaining_time":6.31748456},
{"learn":[0.3081066515],"iteration":255,"passed_time":2.16945866,"remaining_time":6.304989232},
{"learn":[0.3080327604],"iteration":256,"passed_time":2.17736069,"remaining_time":6.294859893},
{"learn":[0.3080013697],"iteration":257,"passed_time":2.185318183,"remaining_time":6.284907333},
{"learn":[0.3079473371],"iteration":258,"passed_time":2.193399712,"remaining_time":6.275325045},
{"learn":[0.3078851434],"iteration":259,"passed_time":2.201689165,"remaining_time":6.266346084},
{"learn":[0.3078039465],"iteration":260,"passed_time":2.209366091,"remaining_time":6.25563809},
{"learn":[0.3077192437],"iteration":261,"passed_time":2.217313904,"remaining_time":6.245716265},
{"learn":[0.307717176],"iteration":262,"passed_time":2.222900976,"remaining_time":6.229193991},
{"learn":[0.3076677896],"iteration":263,"passed_time":2.230626023,"remaining_time":6.218714973},
{"learn":[0.3076448746],"iteration":264,"passed_time":2.238730405,"remaining_time":6.20930886},
{"learn":[0.3075985546],"iteration":265,"passed_time":2.24684157,"remaining_time":6.199931248},
{"learn":[0.3075744459],"iteration":266,"passed_time":2.255044395,"remaining_time":6.190814762},
{"learn":[0.3075277082],"iteration":267,"passed_time":2.263054627,"remaining_time":6.181179055},
{"learn":[0.3074415796],"iteration":268,"passed_time":2.271239169,"remaining_time":6.172029117},
{"learn":[0.3073168113],"iteration":269,"passed_time":2.279274545,"remaining_time":6.162483028},
{"learn":[0.3072761903],"iteration":270,"passed_time":2.287430411,"remaining_time":6.153272213},
{"learn":[0.3072062308],"iteration":271,"passed_time":2.29552789,"remaining_time":6.143912882},
{"learn":[0.3071471689],"iteration":272,"passed_time":2.303476258,"remaining_time":6.134165714},
{"learn":[0.3070967245],"iteration":273,"passed_time":2.311322685,"remaining_time":6.124161568},
{"learn":[0.3069367832],"iteration":274,"passed_time":2.319471325,"remaining_time":6.114969856},
{"learn":[0.3069080478],"iteration":275,"passed_time":2.327086253,"remaining_time":6.104385679},
{"learn":[0.3068820973],"iteration":276,"passed_time":2.334766212,"remaining_time":6.093992675},
{"learn":[0.3068503827],"iteration":277,"passed_time":2.342421826,"remaining_time":6.083555967},
{"learn":[0.306775728],"iteration":278,"passed_time":2.350509341,"remaining_time":6.074255323},
{"learn":[0.3067131767],"iteration":279,"passed_time":2.358366867,"remaining_time":6.064371944},
{"learn":[0.3066309622],"iteration":280,"passed_time":2.366717131,"remaining_time":6.055763762},
{"learn":[0.3065811507],"iteration":281,"passed_time":2.374751681,"remaining_time":6.04635357},
{"learn":[0.3065367534],"iteration":282,"passed_time":2.382629941,"remaining_time":6.036557129},
{"learn":[0.3064517379],"iteration":283,"passed_time":2.39052133,"remaining_time":6.026807298},
{"learn":[0.3064205469],"iteration":284,"passed_time":2.398422856,"remaining_time":6.017095937},
{"learn":[0.3063414954],"iteration":285,"passed_time":2.40634221,"remaining_time":6.007441742},
{"learn":[0.3063172508],"iteration":286,"passed_time":2.413947256,"remaining_time":5.997018794},
{"learn":[0.306227924],"iteration":287,"passed_time":2.422237093,"remaining_time":5.988308369},
{"learn":[0.3062044098],"iteration":288,"passed_time":2.430739115,"remaining_time":5.980122874},
{"learn":[0.3061639556],"iteration":289,"passed_time":2.438784497,"remaining_time":5.970817217},
{"learn":[0.3060822642],"iteration":290,"passed_time":2.446729025,"remaining_time":5.961274498},
{"learn":[0.3060318926],"iteration":291,"passed_time":2.454510826,"remaining_time":5.951348167},
{"learn":[0.3059317447],"iteration":292,"passed_time":2.462696893,"remaining_time":5.942411958},
{"learn":[0.3058697653],"iteration":293,"passed_time":2.470511582,"remaining_time":5.932589038},
{"learn":[0.3058436756],"iteration":294,"passed_time":2.479100905,"remaining_time":5.924630977},
{"learn":[0.3058028054],"iteration":295,"passed_time":2.487008682,"remaining_time":5.915047676},
{"learn":[0.3057406689],"iteration":296,"passed_time":2.495336266,"remaining_time":5.906469344},
{"learn":[0.3057399266],"iteration":297,"passed_time":2.500482429,"remaining_time":5.890398206},
{"learn":[0.3056944291],"iteration":298,"passed_time":2.508308338,"remaining_time":5.88068276},
{"learn":[0.3056637316],"iteration":299,"passed_time":2.515959235,"remaining_time":5.870571548},
{"learn":[0.3055996616],"iteration":300,"passed_time":2.524036982,"remaining_time":5.861467941},
{"learn":[0.3055923187],"iteration":301,"passed_time":2.529914957,"remaining_time":5.847286888},
{"learn":[0.3055560136],"iteration":302,"passed_time":2.537863691,"remaining_time":5.837924068},
{"learn":[0.3055378144],"iteration":303,"passed_time":2.545636162,"remaining_time":5.828167002},
{"learn":[0.305358613],"iteration":304,"passed_time":2.553539365,"remaining_time":5.818720849},
{"learn":[0.3053059325],"iteration":305,"passed_time":2.56175507,"remaining_time":5.809993524},
{"learn":[0.3052173044],"iteration":306,"passed_time":2.569425592,"remaining_time":5.800038877},
{"learn":[0.3051795167],"iteration":307,"passed_time":2.577555499,"remaining_time":5.791131185},
{"learn":[0.3051557805],"iteration":308,"passed_time":2.585610598,"remaining_time":5.782061241},
{"learn":[0.3051216005],"iteration":309,"passed_time":2.594338102,"remaining_time":5.774494484},
{"learn":[0.3050413843],"iteration":310,"passed_time":2.602510505,"remaining_time":5.765690476},
{"learn":[0.3049054246],"iteration":311,"passed_time":2.610347053,"remaining_time":5.756149912},
{"learn":[0.3048591426],"iteration":312,"passed_time":2.618066822,"remaining_time":5.746363919},
{"learn":[0.3048389007],"iteration":313,"passed_time":2.625807967,"remaining_time":5.736637787},
{"learn":[0.3047791673],"iteration":314,"passed_time":2.633646273,"remaining_time":5.727135546},
{"learn":[0.3047187604],"iteration":315,"passed_time":2.641420772,"remaining_time":5.717505722},
{"learn":[0.3046459213],"iteration":316,"passed_time":2.649356448,"remaining_time":5.70823487},
{"learn":[0.3044855559],"iteration":317,"passed_time":2.657186276,"remaining_time":5.69874541},
{"learn":[0.3044348629],"iteration":318,"passed_time":2.664839078,"remaining_time":5.688888439},
{"learn":[0.3043749896],"iteration":319,"passed_time":2.672806577,"remaining_time":5.679713976},
{"learn":[0.3041686157],"iteration":320,"passed_time":2.68060439,"remaining_time":5.670188101},
{"learn":[0.3041612219],"iteration":321,"passed_time":2.686483997,"remaining_time":5.656634006},
{"learn":[0.3040786688],"iteration":322,"passed_time":2.694605554,"remaining_time":5.647826502},
{"learn":[0.3040442611],"iteration":323,"passed_time":2.702739676,"remaining_time":5.639049448},
{"learn":[0.304002599],"iteration":324,"passed_time":2.710821254,"remaining_time":5.63016722},
{"learn":[0.3039602878],"iteration":325,"passed_time":2.719386874,"remaining_time":5.622290653},
{"learn":[0.3038532814],"iteration":326,"passed_time":2.727225746,"remaining_time":5.612914149},
{"learn":[0.3036627622],"iteration":327,"passed_time":2.735072222,"remaining_time":5.603562601},
{"learn":[0.3036200063],"iteration":328,"passed_time":2.744011074,"remaining_time":5.596448118},
{"learn":[0.3035153482],"iteration":329,"passed_time":2.752110483,"remaining_time":5.587618253},
{"learn":[0.3034569116],"iteration":330,"passed_time":2.762582143,"remaining_time":5.583587474},
{"learn":[0.3034239658],"iteration":331,"passed_time":2.771328022,"remaining_time":5.576045538},
{"learn":[0.3033752377],"iteration":332,"passed_time":2.77954965,"remaining_time":5.567446297},
{"learn":[0.3032764329],"iteration":333,"passed_time":2.787973772,"remaining_time":5.559253091},
{"learn":[0.3032366136],"iteration":334,"passed_time":2.797672461,"remaining_time":5.553588617},
{"learn":[0.3031972041],"iteration":335,"passed_time":2.807108367,"remaining_time":5.547380821},
{"learn":[0.3030981868],"iteration":336,"passed_time":2.815825792,"remaining_time":5.539740356},
{"learn":[0.3030440139],"iteration":337,"passed_time":2.824535923,"remaining_time":5.532079233},
{"learn":[0.3029979053],"iteration":338,"passed_time":2.833989561,"remaining_time":5.525861651},
{"learn":[0.3028447701],"iteration":339,"passed_time":2.843098583,"remaining_time":5.518956073},
{"learn":[0.3027568832],"iteration":340,"passed_time":2.853976837,"remaining_time":5.515456703},
{"learn":[0.3026836639],"iteration":341,"passed_time":2.862678665,"remaining_time":5.507726788},
{"learn":[0.302605365],"iteration":342,"passed_time":2.870658279,"remaining_time":5.49860784},
{"learn":[0.302572328],"iteration":343,"passed_time":2.878929585,"remaining_time":5.490051767},
{"learn":[0.3025194115],"iteration":344,"passed_time":2.886887474,"remaining_time":5.480902305},
{"learn":[0.3024907323],"iteration":345,"passed_time":2.89482776,"remaining_time":5.47172646},
{"learn":[0.3024487852],"iteration":346,"passed_time":2.902692477,"remaining_time":5.462415526},
{"learn":[0.3024096483],"iteration":347,"passed_time":2.910345184,"remaining_time":5.45271569},
{"learn":[0.3023104413],"iteration":348,"passed_time":2.91804467,"remaining_time":5.443114842},
{"learn":[0.3022816136],"iteration":349,"passed_time":2.925711243,"remaining_time":5.433463738},
{"learn":[0.3022367242],"iteration":350,"passed_time":2.933970638,"remaining_time":5.424920068},
{"learn":[0.3022158018],"iteration":351,"passed_time":2.941784373,"remaining_time":5.415557596},
{"learn":[0.3021666742],"iteration":352,"passed_time":2.949851194,"remaining_time":5.406667769},
{"learn":[0.3021394977],"iteration":353,"passed_time":2.958337826,"remaining_time":5.398548688},
{"learn":[0.3020869976],"iteration":354,"passed_time":2.966798921,"remaining_time":5.390381139},
{"learn":[0.3020380396],"iteration":355,"passed_time":2.974431486,"remaining_time":5.380713138},
{"learn":[0.3019253606],"iteration":356,"passed_time":2.982086807,"remaining_time":5.371097527},
{"learn":[0.3018717618],"iteration":357,"passed_time":2.990143025,"remaining_time":5.362211793},
{"learn":[0.3018310055],"iteration":358,"passed_time":2.998345076,"remaining_time":5.353591069},
{"learn":[0.301768511],"iteration":359,"passed_time":3.006626982,"remaining_time":5.345114634},
{"learn":[0.3016141385],"iteration":360,"passed_time":3.014615137,"remaining_time":5.336119315},
{"learn":[0.3015795444],"iteration":361,"passed_time":3.023487582,"remaining_time":5.328688059},
{"learn":[0.3015532147],"iteration":362,"passed_time":3.0314656,"remaining_time":5.319679304},
{"learn":[0.3014939674],"iteration":363,"passed_time":3.039760364,"remaining_time":5.311229647},
{"learn":[0.3014536396],"iteration":364,"passed_time":3.048016244,"remaining_time":5.302713191},
{"learn":[0.3013939545],"iteration":365,"passed_time":3.05602552,"remaining_time":5.293770983},
{"learn":[0.3013068666],"iteration":366,"passed_time":3.063835379,"remaining_time":5.284489905},
{"learn":[0.3012836076],"iteration":367,"passed_time":3.0717024,"remaining_time":5.275314991},
{"learn":[0.3011845349],"iteration":368,"passed_time":3.079561399,"remaining_time":5.266133449},
{"learn":[0.3011476291],"iteration":369,"passed_time":3.087449386,"remaining_time":5.257008414},
{"learn":[0.3011081711],"iteration":370,"passed_time":3.095008915,"remaining_time":5.247333173},
{"learn":[0.3010894001],"iteration":371,"passed_time":3.102483939,"remaining_time":5.237526649},
{"learn":[0.3010533687],"iteration":372,"passed_time":3.109947206,"remaining_time":5.227712864},
{"learn":[0.3010132898],"iteration":373,"passed_time":3.117697899,"remaining_time":5.218392739},
{"learn":[0.3009817497],"iteration":374,"passed_time":3.125712544,"remaining_time":5.209520907},
{"learn":[0.3009388199],"iteration":375,"passed_time":3.133446608,"remaining_time":5.200187988},
{"learn":[0.3009015658],"iteration":376,"passed_time":3.14105613,"remaining_time":5.190657742},
{"learn":[0.3007447004],"iteration":377,"passed_time":3.148898218,"remaining_time":5.181520349},
{"learn":[0.300713962],"iteration":378,"passed_time":3.15646556,"remaining_time":5.171939612},
{"learn":[0.3006193246],"iteration":379,"passed_time":3.16478378,"remaining_time":5.163594588},
{"learn":[0.3005053775],"iteration":380,"passed_time":3.172826612,"remaining_time":5.154802291},
{"learn":[0.3003678198],"iteration":381,"passed_time":3.180647943,"remaining_time":5.145655572},
{"learn":[0.3002599078],"iteration":382,"passed_time":3.188541596,"remaining_time":5.136632284},
{"learn":[0.3001640848],"iteration":383,"passed_time":3.196416672,"remaining_time":5.127585078},
{"learn":[0.3000404883],"iteration":384,"passed_time":3.204273269,"remaining_time":5.118514443},
{"learn":[0.2999679552],"iteration":385,"passed_time":3.212303253,"remaining_time":5.1097259},
{"learn":[0.2999055433],"iteration":386,"passed_time":3.221290866,"remaining_time":5.102458142},
{"learn":[0.2998191061],"iteration":387,"passed_time":3.229149914,"remaining_time":5.093401411},
{"learn":[0.2997823158],"iteration":388,"passed_time":3.236870701,"remaining_time":5.084133672},
{"learn":[0.2997539233],"iteration":389,"passed_time":3.244391357,"remaining_time":5.074560841},
{"learn":[0.2997146957],"iteration":390,"passed_time":3.251860434,"remaining_time":5.06491817},
{"learn":[0.2996896383],"iteration":391,"passed_time":3.259486536,"remaining_time":5.055530138},
{"learn":[0.2995639213],"iteration":392,"passed_time":3.267328503,"remaining_time":5.046484482},
{"learn":[0.2995206487],"iteration":393,"passed_time":3.275211772,"remaining_time":5.037508461},
{"learn":[0.2994574266],"iteration":394,"passed_time":3.282996613,"remaining_time":5.028387217},
{"learn":[0.2994329054],"iteration":395,"passed_time":3.290850196,"remaining_time":5.019377572},
{"learn":[0.2993910323],"iteration":396,"passed_time":3.298909432,"remaining_time":5.010686114},
{"learn":[0.2993467119],"iteration":397,"passed_time":3.306824931,"remaining_time":5.001780423},
{"learn":[0.2992879613],"iteration":398,"passed_time":3.314706507,"remaining_time":4.992828599},
{"learn":[0.2992658419],"iteration":399,"passed_time":3.322278122,"remaining_time":4.983417184},
{"learn":[0.2992430837],"iteration":400,"passed_time":3.329839401,"remaining_time":4.973999504},
{"learn":[0.2992221603],"iteration":401,"passed_time":3.337596886,"remaining_time":4.96488293},
{"learn":[0.299177972],"iteration":402,"passed_time":3.34540163,"remaining_time":4.955843109},
{"learn":[0.2991468568],"iteration":403,"passed_time":3.352823305,"remaining_time":4.946244281},
{"learn":[0.2991052785],"iteration":404,"passed_time":3.360723822,"remaining_time":4.937359689},
{"learn":[0.2990168426],"iteration":405,"passed_time":3.369060926,"remaining_time":4.929118695},
{"learn":[0.298981165],"iteration":406,"passed_time":3.378196175,"remaining_time":4.922040127},
{"learn":[0.2989598728],"iteration":407,"passed_time":3.387186994,"remaining_time":4.914741913},
{"learn":[0.2989255527],"iteration":408,"passed_time":3.397376053,"remaining_time":4.909166864},
{"learn":[0.2988669103],"iteration":409,"passed_time":3.406727993,"remaining_time":4.902364672},
{"learn":[0.2988337652],"iteration":410,"passed_time":3.415850427,"remaining_time":4.895221171},
{"learn":[0.2987193933],"iteration":411,"passed_time":3.425398999,"remaining_time":4.888676242},
{"learn":[0.2986755229],"iteration":412,"passed_time":3.434624469,"remaining_time":4.881657539},
{"learn":[0.2986352946],"iteration":413,"passed_time":3.444551987,"remaining_time":4.875621894},
{"learn":[0.298607271],"iteration":414,"passed_time":3.452782768,"remaining_time":4.867175709},
{"learn":[0.2985475365],"iteration":415,"passed_time":3.4623941,"remaining_time":4.860668641},
{"learn":[0.2985279597],"iteration":416,"passed_time":3.471675073,"remaining_time":4.853684814},
{"learn":[0.298500979],"iteration":417,"passed_time":3.480973801,"remaining_time":4.846714718},
{"learn":[0.2984373233],"iteration":418,"passed_time":3.489923328,"remaining_time":4.839249292},
{"learn":[0.298359549],"iteration":419,"passed_time":3.500622385,"remaining_time":4.834192818},
{"learn":[0.298313454],"iteration":420,"passed_time":3.510588287,"remaining_time":4.828101231},
{"learn":[0.2982622034],"iteration":421,"passed_time":3.520687647,"remaining_time":4.822174076},
{"learn":[0.2982320253],"iteration":422,"passed_time":3.529530224,"remaining_time":4.814512858},
{"learn":[0.298202766],"iteration":423,"passed_time":3.537947379,"remaining_time":4.806268137},
{"learn":[0.2981831933],"iteration":424,"passed_time":3.547423019,"remaining_time":4.799454673},
{"learn":[0.2981463035],"iteration":425,"passed_time":3.556876347,"remaining_time":4.792598646},
{"learn":[0.2981209135],"iteration":426,"passed_time":3.565691656,"remaining_time":4.784874283},
{"learn":[0.2980686427],"iteration":427,"passed_time":3.575597669,"remaining_time":4.778602492},
{"learn":[0.29804331],"iteration":428,"passed_time":3.585061911,"remaining_time":4.77172576},
{"learn":[0.2980088068],"iteration":429,"passed_time":3.595820056,"remaining_time":4.766552167},
{"learn":[0.2979673074],"iteration":430,"passed_time":3.605083887,"remaining_time":4.759379888},
{"learn":[0.2979087671],"iteration":431,"passed_time":3.61445145,"remaining_time":4.752334314},
{"learn":[0.2978919667],"iteration":432,"passed_time":3.62362881,"remaining_time":4.74502895},
{"learn":[0.297863497],"iteration":433,"passed_time":3.632630769,"remaining_time":4.73748621},
{"learn":[0.2978301577],"iteration":434,"passed_time":3.64263684,"remaining_time":4.731240953},
{"learn":[0.2977569877],"iteration":435,"passed_time":3.651411581,"remaining_time":4.723385623},
{"learn":[0.2977092955],"iteration":436,"passed_time":3.660575035,"remaining_time":4.716026876},
{"learn":[0.2976635739],"iteration":437,"passed_time":3.669389782,"remaining_time":4.70821246},
{"learn":[0.2975759407],"iteration":438,"passed_time":3.678291794,"remaining_time":4.700505004},
{"learn":[0.2975263214],"iteration":439,"passed_time":3.688170292,"remaining_time":4.694034917},
{"learn":[0.2975018339],"iteration":440,"passed_time":3.696934793,"remaining_time":4.6861373},
{"learn":[0.2974449438],"iteration":441,"passed_time":3.706152504,"remaining_time":4.678807913},
{"learn":[0.2974069646],"iteration":442,"passed_time":3.71439253,"remaining_time":4.670240721},
{"learn":[0.297376704],"iteration":443,"passed_time":3.722405604,"remaining_time":4.661390802},
{"learn":[0.2973306321],"iteration":444,"passed_time":3.732676679,"remaining_time":4.655360802},
{"learn":[0.2973099573],"iteration":445,"passed_time":3.740671652,"remaining_time":4.646484518},
{"learn":[0.2972965609],"iteration":446,"passed_time":3.749351571,"remaining_time":4.63845955},
{"learn":[0.2972733033],"iteration":447,"passed_time":3.757685402,"remaining_time":4.630005227},
{"learn":[0.2972467946],"iteration":448,"passed_time":3.766052865,"remaining_time":4.621592715},
{"learn":[0.2972214138],"iteration":449,"passed_time":3.77422987,"remaining_time":4.612947619},
{"learn":[0.2972012409],"iteration":450,"passed_time":3.782747527,"remaining_time":4.604719274},
{"learn":[0.2971783488],"iteration":451,"passed_time":3.791280404,"remaining_time":4.596508101},
{"learn":[0.2971532659],"iteration":452,"passed_time":3.800085828,"remaining_time":4.58862461},
{"learn":[0.297136965],"iteration":453,"passed_time":3.80849594,"remaining_time":4.580261637},
{"learn":[0.297020157],"iteration":454,"passed_time":3.816521233,"remaining_time":4.571437521},
{"learn":[0.2969950888],"iteration":455,"passed_time":3.824669075,"remaining_time":4.562763107},
{"learn":[0.2969761824],"iteration":456,"passed_time":3.832995718,"remaining_time":4.554303446},
{"learn":[0.2969561524],"iteration":457,"passed_time":3.84124002,"remaining_time":4.545746924},
{"learn":[0.2969392144],"iteration":458,"passed_time":3.849205045,"remaining_time":4.536862591},
{"learn":[0.2968881305],"iteration":459,"passed_time":3.857851377,"remaining_time":4.528782052},
{"learn":[0.2968031776],"iteration":460,"passed_time":3.866376365,"remaining_time":4.520557182},
{"learn":[0.2967834855],"iteration":461,"passed_time":3.874583445,"remaining_time":4.511960808},
{"learn":[0.2967651204],"iteration":462,"passed_time":3.882809764,"remaining_time":4.503388431},
{"learn":[0.2967199119],"iteration":463,"passed_time":3.89105089,"remaining_time":4.494834649},
{"learn":[0.2966790403],"iteration":464,"passed_time":3.899181224,"remaining_time":4.486154742},
{"learn":[0.2966557443],"iteration":465,"passed_time":3.907754893,"remaining_time":4.477985221},
{"learn":[0.296632804],"iteration":466,"passed_time":3.916194279,"remaining_time":4.469660709},
{"learn":[0.2966180861],"iteration":467,"passed_time":3.925405198,"remaining_time":4.462212746},
{"learn":[0.2965986488],"iteration":468,"passed_time":3.934020532,"remaining_time":4.454082948},
{"learn":[0.2965590986],"iteration":469,"passed_time":3.944029735,"remaining_time":4.447522893},
{"learn":[0.2965268387],"iteration":470,"passed_time":3.952532601,"remaining_time":4.439256361},
{"learn":[0.2965060105],"iteration":471,"passed_time":3.961283382,"remaining_time":4.431266156},
{"learn":[0.2964760772],"iteration":472,"passed_time":3.970471555,"remaining_time":4.423760062},
{"learn":[0.2964626246],"iteration":473,"passed_time":3.978906292,"remaining_time":4.41541078},
{"learn":[0.2964269345],"iteration":474,"passed_time":3.988954436,"remaining_time":4.408844376},
{"learn":[0.2963837701],"iteration":475,"passed_time":3.998171829,"remaining_time":4.40134882},
{"learn":[0.2963688814],"iteration":476,"passed_time":4.007209205,"remaining_time":4.393648667},
{"learn":[0.2963586716],"iteration":477,"passed_time":4.016965825,"remaining_time":4.38672837},
{"learn":[0.2963434939],"iteration":478,"passed_time":4.026720768,"remaining_time":4.379794405},
{"learn":[0.2963249969],"iteration":479,"passed_time":4.036276864,"remaining_time":4.372633269},
{"learn":[0.2962923787],"iteration":480,"passed_time":4.045567268,"remaining_time":4.365175492},
{"learn":[0.2962754442],"iteration":481,"passed_time":4.054618724,"remaining_time":4.357453318},
{"learn":[0.2962610045],"iteration":482,"passed_time":4.063213035,"remaining_time":4.349236313},
{"learn":[0.2962305478],"iteration":483,"passed_time":4.072660643,"remaining_time":4.341927462},
{"learn":[0.2961773426],"iteration":484,"passed_time":4.08187035,"remaining_time":4.334357176},
{"learn":[0.2961616043],"iteration":485,"passed_time":4.089890857,"remaining_time":4.325522429},
{"learn":[0.2961336448],"iteration":486,"passed_time":4.099276736,"remaining_time":4.318129293},
{"learn":[0.2961165605],"iteration":487,"passed_time":4.108442958,"remaining_time":4.310497529},
{"learn":[0.2960441129],"iteration":488,"passed_time":4.116654204,"remaining_time":4.301861551},
{"learn":[0.2960276799],"iteration":489,"passed_time":4.125600907,"remaining_time":4.293992781},
{"learn":[0.2960158975],"iteration":490,"passed_time":4.134364434,"remaining_time":4.285929728},
{"learn":[0.2959306453],"iteration":491,"passed_time":4.142489367,"remaining_time":4.277204468},
{"learn":[0.2959041317],"iteration":492,"passed_time":4.151204896,"remaining_time":4.269089011},
{"learn":[0.2958832159],"iteration":493,"passed_time":4.16060373,"remaining_time":4.261671027},
{"learn":[0.2958725064],"iteration":494,"passed_time":4.171696511,"remaining_time":4.255973209},
{"learn":[0.2958561385],"iteration":495,"passed_time":4.180823803,"remaining_time":4.248256445},
{"learn":[0.2958406684],"iteration":496,"passed_time":4.189769008,"remaining_time":4.24034972},
{"learn":[0.2958077967],"iteration":497,"passed_time":4.200039451,"remaining_time":4.233774707},
{"learn":[0.2957938429],"iteration":498,"passed_time":4.208521516,"remaining_time":4.225389338},
{"learn":[0.2957685696],"iteration":499,"passed_time":4.217408873,"remaining_time":4.217408873},
{"learn":[0.295731466],"iteration":500,"passed_time":4.226361129,"remaining_time":4.209489428},
{"learn":[0.2957048245],"iteration":501,"passed_time":4.234507579,"remaining_time":4.200766483},
{"learn":[0.2956924357],"iteration":502,"passed_time":4.242727105,"remaining_time":4.192118034},
{"learn":[0.2956644383],"iteration":503,"passed_time":4.25104713,"remaining_time":4.183570192},
{"learn":[0.2956266886],"iteration":504,"passed_time":4.259362467,"remaining_time":4.175018655},
{"learn":[0.2955895322],"iteration":505,"passed_time":4.267342127,"remaining_time":4.166140337},
{"learn":[0.2955243251],"iteration":506,"passed_time":4.275736968,"remaining_time":4.15766928},
{"learn":[0.2954876058],"iteration":507,"passed_time":4.28358635,"remaining_time":4.148670245},
{"learn":[0.2954723189],"iteration":508,"passed_time":4.291613387,"remaining_time":4.139847098},
{"learn":[0.2954620478],"iteration":509,"passed_time":4.299816722,"remaining_time":4.131196458},
{"learn":[0.2954293638],"iteration":510,"passed_time":4.308711243,"remaining_time":4.123208998},
{"learn":[0.2954173455],"iteration":511,"passed_time":4.317620691,"remaining_time":4.115232221},
{"learn":[0.2953672904],"iteration":512,"passed_time":4.326965926,"remaining_time":4.107665509},
{"learn":[0.2953507033],"iteration":513,"passed_time":4.33664963,"remaining_time":4.100411907},
{"learn":[0.2953373323],"iteration":514,"passed_time":4.345135688,"remaining_time":4.092020988},
{"learn":[0.2953210908],"iteration":515,"passed_time":4.353895857,"remaining_time":4.083886811},
{"learn":[0.2953061034],"iteration":516,"passed_time":4.364890336,"remaining_time":4.077837587},
{"learn":[0.2952968688],"iteration":517,"passed_time":4.373251981,"remaining_time":4.069319411},
{"learn":[0.2952816729],"iteration":518,"passed_time":4.381250516,"remaining_time":4.060465314},
{"learn":[0.2952686472],"iteration":519,"passed_time":4.390737178,"remaining_time":4.052988164},
{"learn":[0.2952582755],"iteration":520,"passed_time":4.40188871,"remaining_time":4.047033958},
{"learn":[0.2952420266],"iteration":521,"passed_time":4.411852003,"remaining_time":4.039971757},
{"learn":[0.2952191749],"iteration":522,"passed_time":4.424488228,"remaining_time":4.0353363},
{"learn":[0.2952073314],"iteration":523,"passed_time":4.435493393,"remaining_time":4.029188654},
{"learn":[0.2951928606],"iteration":524,"passed_time":4.447970955,"remaining_time":4.024354673},
{"learn":[0.2951795117],"iteration":525,"passed_time":4.457879405,"remaining_time":4.017176498},
{"learn":[0.2951415806],"iteration":526,"passed_time":4.46745782,"remaining_time":4.009691744},
{"learn":[0.295122266],"iteration":527,"passed_time":4.478441052,"remaining_time":4.003454879},
{"learn":[0.2951079813],"iteration":528,"passed_time":4.490129163,"remaining_time":3.997827667},
{"learn":[0.2950863987],"iteration":529,"passed_time":4.501600737,"remaining_time":3.991985559},
{"learn":[0.2950481984],"iteration":530,"passed_time":4.511720899,"remaining_time":3.984928628},
{"learn":[0.2950352642],"iteration":531,"passed_time":4.52414459,"remaining_time":3.979886594},
{"learn":[0.2950173307],"iteration":532,"passed_time":4.534469301,"remaining_time":3.972977793},
{"learn":[0.2950039959],"iteration":533,"passed_time":4.546467839,"remaining_time":3.967516879},
{"learn":[0.2949678479],"iteration":534,"passed_time":4.556680897,"remaining_time":3.960479658},
{"learn":[0.2949554449],"iteration":535,"passed_time":4.566388658,"remaining_time":3.952993167},
{"learn":[0.2949397966],"iteration":536,"passed_time":4.577723219,"remaining_time":3.946901025},
{"learn":[0.294923324],"iteration":537,"passed_time":4.588465489,"remaining_time":3.940280773},
{"learn":[0.2949090481],"iteration":538,"passed_time":4.599710549,"remaining_time":3.934075256},
{"learn":[0.2948951655],"iteration":539,"passed_time":4.612493856,"remaining_time":3.929161432},
{"learn":[0.2948520522],"iteration":540,"passed_time":4.622487089,"remaining_time":3.921851338},
{"learn":[0.2948180237],"iteration":541,"passed_time":4.632539453,"remaining_time":3.914581309},
{"learn":[0.2947752563],"iteration":542,"passed_time":4.643675202,"remaining_time":3.908212831},
{"learn":[0.2947388029],"iteration":543,"passed_time":4.654963844,"remaining_time":3.901954987},
{"learn":[0.2946788374],"iteration":544,"passed_time":4.664361623,"remaining_time":3.89410007},
{"learn":[0.2946591054],"iteration":545,"passed_time":4.673509208,"remaining_time":3.886031466},
{"learn":[0.2946487387],"iteration":546,"passed_time":4.681270306,"remaining_time":3.876810693},
{"learn":[0.2946290223],"iteration":547,"passed_time":4.690923291,"remaining_time":3.869155707},
{"learn":[0.2946184616],"iteration":548,"passed_time":4.700225366,"remaining_time":3.861205173},
{"learn":[0.2946042801],"iteration":549,"passed_time":4.709717214,"remaining_time":3.853404993},
{"learn":[0.2945200353],"iteration":550,"passed_time":4.718758247,"remaining_time":3.845231312},
{"learn":[0.2944999442],"iteration":551,"passed_time":4.727467013,"remaining_time":3.836784822},
{"learn":[0.2944884545],"iteration":552,"passed_time":4.735979946,"remaining_time":3.828179089},
{"learn":[0.2944764841],"iteration":553,"passed_time":4.745688961,"remaining_time":3.8205366},
{"learn":[0.2944675154],"iteration":554,"passed_time":4.754340143,"remaining_time":3.812038493},
{"learn":[0.2944578398],"iteration":555,"passed_time":4.763196438,"remaining_time":3.80370363},
{"learn":[0.2944477132],"iteration":556,"passed_time":4.771054331,"remaining_time":3.794572834},
{"learn":[0.2944238113],"iteration":557,"passed_time":4.780088444,"remaining_time":3.786378302},
{"learn":[0.2943873933],"iteration":558,"passed_time":4.789577111,"remaining_time":3.778539366},
{"learn":[0.2943771247],"iteration":559,"passed_time":4.798109974,"remaining_time":3.769943551},
{"learn":[0.2943479774],"iteration":560,"passed_time":4.807207364,"remaining_time":3.76178972},
{"learn":[0.2943363747],"iteration":561,"passed_time":4.817119424,"remaining_time":3.754267452},
{"learn":[0.2943189757],"iteration":562,"passed_time":4.825690241,"remaining_time":3.745695622},
{"learn":[0.294305758],"iteration":563,"passed_time":4.835336651,"remaining_time":3.737955283},
{"learn":[0.2942916147],"iteration":564,"passed_time":4.843651848,"remaining_time":3.729183281},
{"learn":[0.2942804388],"iteration":565,"passed_time":4.852975158,"remaining_time":3.721185898},
{"learn":[0.2942756207],"iteration":566,"passed_time":4.862994271,"remaining_time":3.713715202},
{"learn":[0.2941994602],"iteration":567,"passed_time":4.875375302,"remaining_time":3.70803192},
{"learn":[0.294182571],"iteration":568,"passed_time":4.887133032,"remaining_time":3.701852965},
{"learn":[0.2941119338],"iteration":569,"passed_time":4.895617317,"remaining_time":3.693184994},
{"learn":[0.294080343],"iteration":570,"passed_time":4.905323351,"remaining_time":3.685435583},
{"learn":[0.2940684257],"iteration":571,"passed_time":4.915405605,"remaining_time":3.677960838},
{"learn":[0.2940460695],"iteration":572,"passed_time":4.92370279,"remaining_time":3.669146756},
{"learn":[0.2940214727],"iteration":573,"passed_time":4.933692811,"remaining_time":3.661590832},
{"learn":[0.2940094072],"iteration":574,"passed_time":4.944700924,"remaining_time":3.654778944},
{"learn":[0.2939991073],"iteration":575,"passed_time":4.954640132,"remaining_time":3.647165653},
{"learn":[0.2939807779],"iteration":576,"passed_time":4.965162203,"remaining_time":3.639971598},
{"learn":[0.2939427949],"iteration":577,"passed_time":4.974386894,"remaining_time":3.631818805},
{"learn":[0.2939303015],"iteration":578,"passed_time":4.984814592,"remaining_time":3.624537035},
{"learn":[0.2939124913],"iteration":579,"passed_time":4.995348165,"remaining_time":3.617321085},
{"learn":[0.293898059],"iteration":580,"passed_time":5.011709695,"remaining_time":3.614296665},
{"learn":[0.2938829489],"iteration":581,"passed_time":5.025187214,"remaining_time":3.609155078},
{"learn":[0.2938722941],"iteration":582,"passed_time":5.037103882,"remaining_time":3.602868472},
{"learn":[0.2938538799],"iteration":583,"passed_time":5.04583006,"remaining_time":3.594289906},
{"learn":[0.2938444314],"iteration":584,"passed_time":5.054962113,"remaining_time":3.585998764},
{"learn":[0.2938323585],"iteration":585,"passed_time":5.063978051,"remaining_time":3.577622719},
{"learn":[0.2938225135],"iteration":586,"passed_time":5.071761287,"remaining_time":3.568377192},
{"learn":[0.2938082536],"iteration":587,"passed_time":5.082828447,"remaining_time":3.561437619},
{"learn":[0.2937958636],"iteration":588,"passed_time":5.09266749,"remaining_time":3.55362706},
{"learn":[0.2937821508],"iteration":589,"passed_time":5.103464611,"remaining_time":3.546475408},
{"learn":[0.2937600915],"iteration":590,"passed_time":5.113624585,"remaining_time":3.538870482},
{"learn":[0.2937496605],"iteration":591,"passed_time":5.122953214,"remaining_time":3.530683972},
{"learn":[0.2936968565],"iteration":592,"passed_time":5.132840703,"remaining_time":3.522877177},
{"learn":[0.2936641569],"iteration":593,"passed_time":5.142625866,"remaining_time":3.514993437},
{"learn":[0.2936510341],"iteration":594,"passed_time":5.152749768,"remaining_time":3.507333875},
{"learn":[0.293615748],"iteration":595,"passed_time":5.161789079,"remaining_time":3.498930852},
{"learn":[0.2936086967],"iteration":596,"passed_time":5.172258,"remaining_time":3.491490743},
{"learn":[0.2936039629],"iteration":597,"passed_time":5.186405385,"remaining_time":3.486513319},
{"learn":[0.2935942251],"iteration":598,"passed_time":5.194926054,"remaining_time":3.477738477},
{"learn":[0.2935831624],"iteration":599,"passed_time":5.204220035,"remaining_time":3.469480023},
{"learn":[0.2935724808],"iteration":600,"passed_time":5.213815014,"remaining_time":3.461417954},
{"learn":[0.2935650922],"iteration":601,"passed_time":5.222509729,"remaining_time":3.452755602},
{"learn":[0.2935353012],"iteration":602,"passed_time":5.2322715,"remaining_time":3.444795664},
{"learn":[0.2935248314],"iteration":603,"passed_time":5.241004662,"remaining_time":3.436155374},
{"learn":[0.2935158916],"iteration":604,"passed_time":5.249459182,"remaining_time":3.427332854},
{"learn":[0.2934927501],"iteration":605,"passed_time":5.25822967,"remaining_time":3.41871698},
{"learn":[0.2934606635],"iteration":606,"passed_time":5.267119383,"remaining_time":3.410177788},
{"learn":[0.2934475103],"iteration":607,"passed_time":5.276122383,"remaining_time":3.401710484},
{"learn":[0.2934383698],"iteration":608,"passed_time":5.284718094,"remaining_time":3.392979926},
{"learn":[0.2934316851],"iteration":609,"passed_time":5.293548105,"remaining_time":3.384399608},
{"learn":[0.2934135006],"iteration":610,"passed_time":5.302520928,"remaining_time":3.375909396},
{"learn":[0.2933788313],"iteration":611,"passed_time":5.313023949,"remaining_time":3.368387733},
{"learn":[0.2933459857],"iteration":612,"passed_time":5.321959273,"remaining_time":3.359866621},
{"learn":[0.2933297501],"iteration":613,"passed_time":5.330517018,"remaining_time":3.35110679},
{"learn":[0.2933120963],"iteration":614,"passed_time":5.339176462,"remaining_time":3.342411281},
{"learn":[0.2933025878],"iteration":615,"passed_time":5.347221476,"remaining_time":3.333332868},
{"learn":[0.2932343341],"iteration":616,"passed_time":5.355780886,"remaining_time":3.324577114},
{"learn":[0.2931855872],"iteration":617,"passed_time":5.36677744,"remaining_time":3.31732845},
{"learn":[0.2931633541],"iteration":618,"passed_time":5.376673269,"remaining_time":3.309390171},
{"learn":[0.2930822162],"iteration":619,"passed_time":5.386505299,"remaining_time":3.301406474},
{"learn":[0.2930402554],"iteration":620,"passed_time":5.396737601,"remaining_time":3.293661113},
{"learn":[0.2930224084],"iteration":621,"passed_time":5.407851931,"remaining_time":3.286443778},
{"learn":[0.2930087844],"iteration":622,"passed_time":5.419849844,"remaining_time":3.279748621},
{"learn":[0.29300485],"iteration":623,"passed_time":5.431315309,"remaining_time":3.272715635},
{"learn":[0.2929654709],"iteration":624,"passed_time":5.440984445,"remaining_time":3.264590667},
{"learn":[0.2929571691],"iteration":625,"passed_time":5.449752677,"remaining_time":3.255922526},
{"learn":[0.2929514688],"iteration":626,"passed_time":5.45928649,"remaining_time":3.247709507},
{"learn":[0.2929272651],"iteration":627,"passed_time":5.468536895,"remaining_time":3.239324403},
{"learn":[0.2929111006],"iteration":628,"passed_time":5.478150922,"remaining_time":3.231151021},
{"learn":[0.2929027257],"iteration":629,"passed_time":5.487319548,"remaining_time":3.22271148},
{"learn":[0.2928898708],"iteration":630,"passed_time":5.496106387,"remaining_time":3.214046366},
{"learn":[0.292882912],"iteration":631,"passed_time":5.505306805,"remaining_time":3.205621684},
{"learn":[0.2928766549],"iteration":632,"passed_time":5.514631811,"remaining_time":3.197266785},
{"learn":[0.2928684503],"iteration":633,"passed_time":5.525171064,"remaining_time":3.189609794},
{"learn":[0.2928619921],"iteration":634,"passed_time":5.534657781,"remaining_time":3.181338725},
{"learn":[0.2928451498],"iteration":635,"passed_time":5.543719087,"remaining_time":3.172820358},
{"learn":[0.2928355462],"iteration":636,"passed_time":5.552741935,"remaining_time":3.164278371},
{"learn":[0.2928267998],"iteration":637,"passed_time":5.561797564,"remaining_time":3.155753477},
{"learn":[0.2928057251],"iteration":638,"passed_time":5.571073538,"remaining_time":3.147351404},
{"learn":[0.2927932244],"iteration":639,"passed_time":5.580381118,"remaining_time":3.138964379},
{"learn":[0.2927878984],"iteration":640,"passed_time":5.590021232,"remaining_time":3.130760721},
{"learn":[0.2927843777],"iteration":641,"passed_time":5.599216142,"remaining_time":3.122304328},
{"learn":[0.2927352169],"iteration":642,"passed_time":5.608157326,"remaining_time":3.113704768},
{"learn":[0.2926965084],"iteration":643,"passed_time":5.617045845,"remaining_time":3.105075032},
{"learn":[0.292686173],"iteration":644,"passed_time":5.626768905,"remaining_time":3.096903816},
{"learn":[0.2926648826],"iteration":645,"passed_time":5.635740359,"remaining_time":3.088315924},
{"learn":[0.2926566616],"iteration":646,"passed_time":5.644888518,"remaining_time":3.079823256},
{"learn":[0.2926348819],"iteration":647,"passed_time":5.655316152,"remaining_time":3.072023589},
{"learn":[0.2926233326],"iteration":648,"passed_time":5.66421319,"remaining_time":3.063388027},
{"learn":[0.2925745001],"iteration":649,"passed_time":5.673370677,"remaining_time":3.054891903},
{"learn":[0.2925489919],"iteration":650,"passed_time":5.68303723,"remaining_time":3.046666656},
{"learn":[0.2925428695],"iteration":651,"passed_time":5.692210263,"remaining_time":3.038173576},
{"learn":[0.292531641],"iteration":652,"passed_time":5.701063994,"remaining_time":3.029508738},
{"learn":[0.2924958432],"iteration":653,"passed_time":5.71042169,"remaining_time":3.021109946},
{"learn":[0.2924819361],"iteration":654,"passed_time":5.719563497,"remaining_time":3.012594514},
{"learn":[0.2924709149],"iteration":655,"passed_time":5.728615941,"remaining_time":3.00403031},
{"learn":[0.2924484327],"iteration":656,"passed_time":5.737880132,"remaining_time":2.995575168},
{"learn":[0.2924417975],"iteration":657,"passed_time":5.747332776,"remaining_time":2.987215516},
{"learn":[0.2924279995],"iteration":658,"passed_time":5.756257805,"remaining_time":2.978579532},
{"learn":[0.2924240966],"iteration":659,"passed_time":5.765721041,"remaining_time":2.97021993},
{"learn":[0.2923969821],"iteration":660,"passed_time":5.774978154,"remaining_time":2.961751277},
{"learn":[0.2923659765],"iteration":661,"passed_time":5.784401917,"remaining_time":2.953365329},
{"learn":[0.2923579924],"iteration":662,"passed_time":5.793907548,"remaining_time":2.945017864},
{"learn":[0.292351921],"iteration":663,"passed_time":5.802815721,"remaining_time":2.936364582},
{"learn":[0.2923439603],"iteration":664,"passed_time":5.81344449,"remaining_time":2.928577299},
{"learn":[0.2923130122],"iteration":665,"passed_time":5.822706138,"remaining_time":2.920095871},
{"learn":[0.2922765881],"iteration":666,"passed_time":5.833159874,"remaining_time":2.912207253},
{"learn":[0.2922586179],"iteration":667,"passed_time":5.84247626,"remaining_time":2.903745686},
{"learn":[0.2922056208],"iteration":668,"passed_time":5.851772994,"remaining_time":2.89527184},
{"learn":[0.292195392],"iteration":669,"passed_time":5.861034291,"remaining_time":2.886778083},
{"learn":[0.2921918173],"iteration":670,"passed_time":5.869800001,"remaining_time":2.878039047},
{"learn":[0.2921836881],"iteration":671,"passed_time":5.87977943,"remaining_time":2.869892341},
{"learn":[0.2921491486],"iteration":672,"passed_time":5.889661498,"remaining_time":2.861692882},
{"learn":[0.2921456101],"iteration":673,"passed_time":5.898506484,"remaining_time":2.852986816},
{"learn":[0.2921064429],"iteration":674,"passed_time":5.908055355,"remaining_time":2.844619245},
{"learn":[0.2920868515],"iteration":675,"passed_time":5.917265973,"remaining_time":2.836086058},
{"learn":[0.2920623135],"iteration":676,"passed_time":5.928437861,"remaining_time":2.828486601},
{"learn":[0.292028267],"iteration":677,"passed_time":5.938118257,"remaining_time":2.820168258},
{"learn":[0.2919833453],"iteration":678,"passed_time":5.948473963,"remaining_time":2.812165158},
{"learn":[0.2919397665],"iteration":679,"passed_time":5.957685577,"remaining_time":2.803616742},
{"learn":[0.2919103616],"iteration":680,"passed_time":5.968228032,"remaining_time":2.795689783},
{"learn":[0.2919032398],"iteration":681,"passed_time":5.977594213,"remaining_time":2.787206686},
{"learn":[0.2918662986],"iteration":682,"passed_time":5.986781935,"remaining_time":2.778638175},
{"learn":[0.2918616314],"iteration":683,"passed_time":5.995690199,"remaining_time":2.769938747},
{"learn":[0.2918533062],"iteration":684,"passed_time":6.004611639,"remaining_time":2.761244768},
{"learn":[0.2918457941],"iteration":685,"passed_time":6.013277512,"remaining_time":2.752433147},
{"learn":[0.2918037934],"iteration":686,"passed_time":6.02242629,"remaining_time":2.743841963},
{"learn":[0.2917909607],"iteration":687,"passed_time":6.031595968,"remaining_time":2.735258637},
{"learn":[0.2917832098],"iteration":688,"passed_time":6.040564445,"remaining_time":2.72658279},
{"learn":[0.291774253],"iteration":689,"passed_time":6.049186996,"remaining_time":2.71775068},
{"learn":[0.291768131],"iteration":690,"passed_time":6.058433848,"remaining_time":2.709198349},
{"learn":[0.2917563688],"iteration":691,"passed_time":6.067028247,"remaining_time":2.700353613},
{"learn":[0.2917537704],"iteration":692,"passed_time":6.075563935,"remaining_time":2.69148359},
{"learn":[0.2917425093],"iteration":693,"passed_time":6.084194799,"remaining_time":2.682656497},
{"learn":[0.2917337693],"iteration":694,"passed_time":6.09343833,"remaining_time":2.674098836},
{"learn":[0.2917269807],"iteration":695,"passed_time":6.102329359,"remaining_time":2.665385237},
{"learn":[0.2917166407],"iteration":696,"passed_time":6.11118522,"remaining_time":2.656655841},
{"learn":[0.2916705152],"iteration":697,"passed_time":6.119855496,"remaining_time":2.647845788},
{"learn":[0.2916077648],"iteration":698,"passed_time":6.129135472,"remaining_time":2.63929868},
{"learn":[0.2915879554],"iteration":699,"passed_time":6.137190763,"remaining_time":2.630224613},
{"learn":[0.2915811127],"iteration":700,"passed_time":6.145187407,"remaining_time":2.621128438},
{"learn":[0.2915514919],"iteration":701,"passed_time":6.153495772,"remaining_time":2.612167721},
{"learn":[0.2915193878],"iteration":702,"passed_time":6.162089953,"remaining_time":2.60332961},
{"learn":[0.2915052798],"iteration":703,"passed_time":6.170743379,"remaining_time":2.594517102},
{"learn":[0.2915001974],"iteration":704,"passed_time":6.178750623,"remaining_time":2.585434658},
{"learn":[0.2914963919],"iteration":705,"passed_time":6.187322975,"remaining_time":2.576590587},
{"learn":[0.2914594506],"iteration":706,"passed_time":6.19571883,"remaining_time":2.56767414},
{"learn":[0.2914374309],"iteration":707,"passed_time":6.204391127,"remaining_time":2.558873177},
{"learn":[0.2914274839],"iteration":708,"passed_time":6.2127751,"remaining_time":2.549954237},
{"learn":[0.2914172404],"iteration":709,"passed_time":6.221540199,"remaining_time":2.541192476},
{"learn":[0.2913900912],"iteration":710,"passed_time":6.230460752,"remaining_time":2.532493892},
{"learn":[0.2913818886],"iteration":711,"passed_time":6.23862199,"remaining_time":2.523487546},
{"learn":[0.2913505987],"iteration":712,"passed_time":6.246698433,"remaining_time":2.514449439},
{"learn":[0.291327936],"iteration":713,"passed_time":6.255689276,"remaining_time":2.505780298},
{"learn":[0.2913173938],"iteration":714,"passed_time":6.263969861,"remaining_time":2.496827147},
{"learn":[0.2913036515],"iteration":715,"passed_time":6.272565703,"remaining_time":2.488000921},
{"learn":[0.2912970514],"iteration":716,"passed_time":6.280690562,"remaining_time":2.478989441},
{"learn":[0.2912898549],"iteration":717,"passed_time":6.288898737,"remaining_time":2.470013153},
{"learn":[0.2912793067],"iteration":718,"passed_time":6.296822767,"remaining_time":2.460927952},
{"learn":[0.2912653183],"iteration":719,"passed_time":6.305451281,"remaining_time":2.452119943},
{"learn":[0.2912560852],"iteration":720,"passed_time":6.313483627,"remaining_time":2.443081736},
{"learn":[0.2912452429],"iteration":721,"passed_time":6.321583731,"remaining_time":2.434072406},
{"learn":[0.2912359517],"iteration":722,"passed_time":6.329820869,"remaining_time":2.425118092},
{"learn":[0.2912018638],"iteration":723,"passed_time":6.337915157,"remaining_time":2.416111303},
{"learn":[0.2911700269],"iteration":724,"passed_time":6.346849581,"remaining_time":2.407425703},
{"learn":[0.2911549655],"iteration":725,"passed_time":6.355372542,"remaining_time":2.398584127},
{"learn":[0.291150547],"iteration":726,"passed_time":6.364132336,"remaining_time":2.389832363},
{"learn":[0.2911134431],"iteration":727,"passed_time":6.372637611,"remaining_time":2.380985481},
{"learn":[0.2911061667],"iteration":728,"passed_time":6.381054937,"remaining_time":2.372106842},
{"learn":[0.2910875523],"iteration":729,"passed_time":6.38891437,"remaining_time":2.363023123},
{"learn":[0.2910729705],"iteration":730,"passed_time":6.397602656,"remaining_time":2.354247763},
{"learn":[0.2910460099],"iteration":731,"passed_time":6.406461883,"remaining_time":2.345535225},
{"learn":[0.2910382631],"iteration":732,"passed_time":6.414705954,"remaining_time":2.336598212},
{"learn":[0.2910311878],"iteration":733,"passed_time":6.422861035,"remaining_time":2.327630838},
{"learn":[0.2909945049],"iteration":734,"passed_time":6.431707801,"remaining_time":2.318915057},
{"learn":[0.2909622578],"iteration":735,"passed_time":6.440146472,"remaining_time":2.310052539},
{"learn":[0.2909335796],"iteration":736,"passed_time":6.448437,"remaining_time":2.301138305},
{"learn":[0.2908910807],"iteration":737,"passed_time":6.456746139,"remaining_time":2.292232369},
{"learn":[0.2908803807],"iteration":738,"passed_time":6.464874055,"remaining_time":2.283264044},
{"learn":[0.2908711205],"iteration":739,"passed_time":6.472958937,"remaining_time":2.27428287},
{"learn":[0.2908628495],"iteration":740,"passed_time":6.481052592,"remaining_time":2.265307181},
{"learn":[0.2908279984],"iteration":741,"passed_time":6.489522711,"remaining_time":2.25646477},
{"learn":[0.2908033674],"iteration":742,"passed_time":6.497565567,"remaining_time":2.247475573},
{"learn":[0.2907986053],"iteration":743,"passed_time":6.505897473,"remaining_time":2.238588378},
{"learn":[0.2907902859],"iteration":744,"passed_time":6.514104596,"remaining_time":2.229659962},
{"learn":[0.2907815199],"iteration":745,"passed_time":6.522758171,"remaining_time":2.22088549},
{"learn":[0.2907723871],"iteration":746,"passed_time":6.531096254,"remaining_time":2.212004488},
{"learn":[0.2907026962],"iteration":747,"passed_time":6.539943745,"remaining_time":2.203296556},
{"learn":[0.2906914833],"iteration":748,"passed_time":6.548398657,"remaining_time":2.194456693},
{"learn":[0.2906818925],"iteration":749,"passed_time":6.5566784,"remaining_time":2.185559467},
{"learn":[0.2906525964],"iteration":750,"passed_time":6.564739591,"remaining_time":2.176591422},
{"learn":[0.2906408658],"iteration":751,"passed_time":6.57260145,"remaining_time":2.167560053},
{"learn":[0.2906258583],"iteration":752,"passed_time":6.580669977,"remaining_time":2.158599581},
{"learn":[0.2906223005],"iteration":753,"passed_time":6.58838906,"remaining_time":2.149527465},
{"learn":[0.2906127604],"iteration":754,"passed_time":6.596348346,"remaining_time":2.140536881},
{"learn":[0.290581634],"iteration":755,"passed_time":6.604562208,"remaining_time":2.131631189},
{"learn":[0.2905633665],"iteration":756,"passed_time":6.612824222,"remaining_time":2.122742782},
{"learn":[0.2905500157],"iteration":757,"passed_time":6.620972864,"remaining_time":2.113819833},
{"learn":[0.2905323856],"iteration":758,"passed_time":6.629100063,"remaining_time":2.104892115},
{"learn":[0.2905297204],"iteration":759,"passed_time":6.637197574,"remaining_time":2.095957129},
{"learn":[0.2904683211],"iteration":760,"passed_time":6.645928651,"remaining_time":2.087223321},
{"learn":[0.2904610085],"iteration":761,"passed_time":6.653851183,"remaining_time":2.078236984},
{"learn":[0.2904520175],"iteration":762,"passed_time":6.662098333,"remaining_time":2.069354266},
{"learn":[0.2904495015],"iteration":763,"passed_time":6.670143161,"remaining_time":2.060410715},
{"learn":[0.2904183699],"iteration":764,"passed_time":6.678270053,"remaining_time":2.051494722},
{"learn":[0.2904089887],"iteration":765,"passed_time":6.686582856,"remaining_time":2.042637583},
{"learn":[0.2904012891],"iteration":766,"passed_time":6.69434133,"remaining_time":2.033613468},
{"learn":[0.290398878],"iteration":767,"passed_time":6.703185676,"remaining_time":2.024920673},
{"learn":[0.2903709183],"iteration":768,"passed_time":6.711723191,"remaining_time":2.016135315},
{"learn":[0.2903646756],"iteration":769,"passed_time":6.720359279,"remaining_time":2.007380044},
{"learn":[0.2903310722],"iteration":770,"passed_time":6.728940159,"remaining_time":1.998608685},
{"learn":[0.2903043281],"iteration":771,"passed_time":6.737863724,"remaining_time":1.989939027},
{"learn":[0.2902623022],"iteration":772,"passed_time":6.745644272,"remaining_time":1.980933053},
{"learn":[0.2902518981],"iteration":773,"passed_time":6.753680663,"remaining_time":1.972004948},
{"learn":[0.2902417826],"iteration":774,"passed_time":6.761425474,"remaining_time":1.962994492},
{"learn":[0.2902092587],"iteration":775,"passed_time":6.769615964,"remaining_time":1.954115948},
{"learn":[0.2902021184],"iteration":776,"passed_time":6.776740207,"remaining_time":1.944933161},
{"learn":[0.2901854385],"iteration":777,"passed_time":6.784772437,"remaining_time":1.936014757},
{"learn":[0.2901299137],"iteration":778,"passed_time":6.792718618,"remaining_time":1.927074216},
{"learn":[0.2901055374],"iteration":779,"passed_time":6.800945269,"remaining_time":1.918215332},
{"learn":[0.2901022065],"iteration":780,"passed_time":6.808429749,"remaining_time":1.909149955},
{"learn":[0.2900998652],"iteration":781,"passed_time":6.816125175,"remaining_time":1.900147427},
{"learn":[0.2900748565],"iteration":782,"passed_time":6.824189178,"remaining_time":1.891250385},
{"learn":[0.2900556165],"iteration":783,"passed_time":6.831983258,"remaining_time":1.882281102},
{"learn":[0.2900428032],"iteration":784,"passed_time":6.839899997,"remaining_time":1.873348407},
{"learn":[0.2900406801],"iteration":785,"passed_time":6.847330859,"remaining_time":1.86428601},
{"learn":[0.2900332745],"iteration":786,"passed_time":6.854667822,"remaining_time":1.855202346},
{"learn":[0.2900096989],"iteration":787,"passed_time":6.862587519,"remaining_time":1.846279891},
{"learn":[0.2899622562],"iteration":788,"passed_time":6.870122161,"remaining_time":1.837257004},
{"learn":[0.2899302607],"iteration":789,"passed_time":6.877845073,"remaining_time":1.828287931},
{"learn":[0.289903435],"iteration":790,"passed_time":6.885801196,"remaining_time":1.819383628},
{"learn":[0.2898382609],"iteration":791,"passed_time":6.894437343,"remaining_time":1.810660312},
{"learn":[0.2897932507],"iteration":792,"passed_time":6.903255974,"remaining_time":1.801984851},
{"learn":[0.2897666956],"iteration":793,"passed_time":6.911788108,"remaining_time":1.793234698},
{"learn":[0.2897498743],"iteration":794,"passed_time":6.919714494,"remaining_time":1.784328895},
{"learn":[0.2897196374],"iteration":795,"passed_time":6.928016234,"remaining_time":1.775521748},
{"learn":[0.2897043671],"iteration":796,"passed_time":6.937184166,"remaining_time":1.766936494},
{"learn":[0.2897005022],"iteration":797,"passed_time":6.94500221,"remaining_time":1.758008078},
{"learn":[0.2896933699],"iteration":798,"passed_time":6.952200173,"remaining_time":1.748926452},
{"learn":[0.2896630104],"iteration":799,"passed_time":6.960017719,"remaining_time":1.74000443},
{"learn":[0.289660936],"iteration":800,"passed_time":6.968063268,"remaining_time":1.731141811},
{"learn":[0.2896456883],"iteration":801,"passed_time":6.97578558,"remaining_time":1.722201427},
{"learn":[0.2896401469],"iteration":802,"passed_time":6.983678711,"remaining_time":1.713305985},
{"learn":[0.2896332608],"iteration":803,"passed_time":6.991081173,"remaining_time":1.70429342},
{"learn":[0.2896193756],"iteration":804,"passed_time":6.998694145,"remaining_time":1.695335849},
{"learn":[0.2895916845],"iteration":805,"passed_time":7.006241223,"remaining_time":1.686365753},
{"learn":[0.2895580319],"iteration":806,"passed_time":7.014023288,"remaining_time":1.677455384},
{"learn":[0.2895494555],"iteration":807,"passed_time":7.021544298,"remaining_time":1.668485774},
{"learn":[0.2895071398],"iteration":808,"passed_time":7.029416059,"remaining_time":1.659602555},
{"learn":[0.289485665],"iteration":809,"passed_time":7.037345555,"remaining_time":1.650735377},
{"learn":[0.2894781926],"iteration":810,"passed_time":7.044327336,"remaining_time":1.641649651},
{"learn":[0.2894717318],"iteration":811,"passed_time":7.051853578,"remaining_time":1.632695163},
{"learn":[0.2894701332],"iteration":812,"passed_time":7.060170217,"remaining_time":1.623925991},
{"learn":[0.2894185677],"iteration":813,"passed_time":7.068218825,"remaining_time":1.615096685},
{"learn":[0.2894095565],"iteration":814,"passed_time":7.076125528,"remaining_time":1.606237083},
{"learn":[0.2894004642],"iteration":815,"passed_time":7.083963293,"remaining_time":1.597364272},
{"learn":[0.2893734172],"iteration":816,"passed_time":7.092031786,"remaining_time":1.588545675},
{"learn":[0.2893518897],"iteration":817,"passed_time":7.100300269,"remaining_time":1.57977341},
{"learn":[0.28934465],"iteration":818,"passed_time":7.108211711,"remaining_time":1.570923467},
{"learn":[0.2893411193],"iteration":819,"passed_time":7.115782372,"remaining_time":1.562001009},
{"learn":[0.2893316526],"iteration":820,"passed_time":7.123673017,"remaining_time":1.553151608},
{"learn":[0.2892968002],"iteration":821,"passed_time":7.131718576,"remaining_time":1.544338086},
{"learn":[0.2892684062],"iteration":822,"passed_time":7.139796883,"remaining_time":1.535533473},
{"learn":[0.2892667188],"iteration":823,"passed_time":7.152951105,"remaining_time":1.527814799},
{"learn":[0.2892511647],"iteration":824,"passed_time":7.164588389,"remaining_time":1.519761173},
{"learn":[0.2892451499],"iteration":825,"passed_time":7.174869551,"remaining_time":1.511413198},
{"learn":[0.2892410577],"iteration":826,"passed_time":7.185609135,"remaining_time":1.503156445},
{"learn":[0.2892341416],"iteration":827,"passed_time":7.196601555,"remaining_time":1.494946217},
{"learn":[0.2892277283],"iteration":828,"passed_time":7.207160773,"remaining_time":1.486639918},
{"learn":[0.2892021309],"iteration":829,"passed_time":7.217747731,"remaining_time":1.478333873},
{"learn":[0.2891869276],"iteration":830,"passed_time":7.226691662,"remaining_time":1.469688196},
{"learn":[0.2891791828],"iteration":831,"passed_time":7.235147199,"remaining_time":1.460943184},
{"learn":[0.2891715365],"iteration":832,"passed_time":7.244491696,"remaining_time":1.452377087},
{"learn":[0.289129358],"iteration":833,"passed_time":7.252861999,"remaining_time":1.443615218},
{"learn":[0.2891199396],"iteration":834,"passed_time":7.260727265,"remaining_time":1.434754489},
{"learn":[0.2891116902],"iteration":835,"passed_time":7.26840357,"remaining_time":1.425859073},
{"learn":[0.2890970148],"iteration":836,"passed_time":7.276768989,"remaining_time":1.417100771},
{"learn":[0.2890595585],"iteration":837,"passed_time":7.284544223,"remaining_time":1.408229313},
{"learn":[0.2890510007],"iteration":838,"passed_time":7.292370779,"remaining_time":1.399370316},
{"learn":[0.2890248793],"iteration":839,"passed_time":7.300236957,"remaining_time":1.390521325},
{"learn":[0.2890111662],"iteration":840,"passed_time":7.307701933,"remaining_time":1.38159882},
{"learn":[0.2889780652],"iteration":841,"passed_time":7.315394717,"remaining_time":1.372722524},
{"learn":[0.2889743634],"iteration":842,"passed_time":7.323028349,"remaining_time":1.36383802},
{"learn":[0.2889671356],"iteration":843,"passed_time":7.330465378,"remaining_time":1.354920141},
{"learn":[0.28893462],"iteration":844,"passed_time":7.338073754,"remaining_time":1.346037197},
{"learn":[0.2889210575],"iteration":845,"passed_time":7.346067492,"remaining_time":1.337227416},
{"learn":[0.2888972864],"iteration":846,"passed_time":7.354026928,"remaining_time":1.328413365},
{"learn":[0.2888797307],"iteration":847,"passed_time":7.361971524,"remaining_time":1.319598669},
{"learn":[0.288853346],"iteration":848,"passed_time":7.370134926,"remaining_time":1.31082494},
{"learn":[0.2888451138],"iteration":849,"passed_time":7.377960494,"remaining_time":1.301993028},
{"learn":[0.2888085082],"iteration":850,"passed_time":7.386081702,"remaining_time":1.293215245},
{"learn":[0.2887837561],"iteration":851,"passed_time":7.394019509,"remaining_time":1.284407145},
{"learn":[0.2887751829],"iteration":852,"passed_time":7.401957982,"remaining_time":1.2756012},
{"learn":[0.2887634458],"iteration":853,"passed_time":7.410008377,"remaining_time":1.26681642},
{"learn":[0.2887455003],"iteration":854,"passed_time":7.417742481,"remaining_time":1.257979719},
{"learn":[0.2887330047],"iteration":855,"passed_time":7.425489944,"remaining_time":1.249147841},
{"learn":[0.2887220644],"iteration":856,"passed_time":7.433362513,"remaining_time":1.240339369},
{"learn":[0.2887201461],"iteration":857,"passed_time":7.441879693,"remaining_time":1.231639763},
{"learn":[0.2887153038],"iteration":858,"passed_time":7.450102306,"remaining_time":1.22289223},
{"learn":[0.2887094896],"iteration":859,"passed_time":7.458018186,"remaining_time":1.214095984},
{"learn":[0.2887045018],"iteration":860,"passed_time":7.465914676,"remaining_time":1.205298653},
{"learn":[0.2886946372],"iteration":861,"passed_time":7.473825476,"remaining_time":1.196505703},
{"learn":[0.2886892937],"iteration":862,"passed_time":7.48143043,"remaining_time":1.187666244},
{"learn":[0.2886855575],"iteration":863,"passed_time":7.488783888,"remaining_time":1.178790056},
{"learn":[0.2886835028],"iteration":864,"passed_time":7.496530469,"remaining_time":1.169978744},
{"learn":[0.2886449999],"iteration":865,"passed_time":7.50414944,"remaining_time":1.161150144},
{"learn":[0.2886049513],"iteration":866,"passed_time":7.512709718,"remaining_time":1.152468734},
{"learn":[0.2885994478],"iteration":867,"passed_time":7.519687601,"remaining_time":1.143546962},
{"learn":[0.2885679854],"iteration":868,"passed_time":7.527401227,"remaining_time":1.134740576},
{"learn":[0.288540473],"iteration":869,"passed_time":7.534693233,"remaining_time":1.125873701},
{"learn":[0.2885135058],"iteration":870,"passed_time":7.542300556,"remaining_time":1.117057143},
{"learn":[0.2884905788],"iteration":871,"passed_time":7.550351866,"remaining_time":1.108308531},
{"learn":[0.2884754417],"iteration":872,"passed_time":7.558003968,"remaining_time":1.099503441},
{"learn":[0.2884739129],"iteration":873,"passed_time":7.565592866,"remaining_time":1.090691878},
{"learn":[0.2884680126],"iteration":874,"passed_time":7.572643668,"remaining_time":1.081806238},
{"learn":[0.2884660692],"iteration":875,"passed_time":7.580321454,"remaining_time":1.073013539},
{"learn":[0.2884520344],"iteration":876,"passed_time":7.588134074,"remaining_time":1.064242293},
{"learn":[0.2884505434],"iteration":877,"passed_time":7.595766162,"remaining_time":1.055448145},
{"learn":[0.2884390669],"iteration":878,"passed_time":7.603519264,"remaining_time":1.0466733},
{"learn":[0.2884358429],"iteration":879,"passed_time":7.610990326,"remaining_time":1.037862317},
{"learn":[0.288428226],"iteration":880,"passed_time":7.618907514,"remaining_time":1.029114636},
{"learn":[0.2884021126],"iteration":881,"passed_time":7.626591666,"remaining_time":1.020337661},
{"learn":[0.2883936945],"iteration":882,"passed_time":7.63401192,"remaining_time":1.011528193},
{"learn":[0.2883866837],"iteration":883,"passed_time":7.641798422,"remaining_time":1.002769929},
{"learn":[0.2883734451],"iteration":884,"passed_time":7.64966356,"remaining_time":0.9940240784},
{"learn":[0.2883655659],"iteration":885,"passed_time":7.658291572,"remaining_time":0.9853783738},
{"learn":[0.2883421226],"iteration":886,"passed_time":7.666224949,"remaining_time":0.9766442156},
{"learn":[0.2882988299],"iteration":887,"passed_time":7.674340941,"remaining_time":0.9679348935},
{"learn":[0.2882903844],"iteration":888,"passed_time":7.682390582,"remaining_time":0.9592186216},
{"learn":[0.2882869384],"iteration":889,"passed_time":7.6899524,"remaining_time":0.950443555},
{"learn":[0.2882601323],"iteration":890,"passed_time":7.697865121,"remaining_time":0.9417141393},
{"learn":[0.2882530659],"iteration":891,"passed_time":7.705414282,"remaining_time":0.9329425364},
{"learn":[0.2882451506],"iteration":892,"passed_time":7.713501507,"remaining_time":0.9242381425},
{"learn":[0.2882380067],"iteration":893,"passed_time":7.721108193,"remaining_time":0.9154781526},
{"learn":[0.2882042461],"iteration":894,"passed_time":7.729018374,"remaining_time":0.9067563456},
{"learn":[0.288179812],"iteration":895,"passed_time":7.737060854,"remaining_time":0.8980517063},
{"learn":[0.2881723554],"iteration":896,"passed_time":7.745157614,"remaining_time":0.8893547762},
{"learn":[0.2881443887],"iteration":897,"passed_time":7.753043517,"remaining_time":0.8806352324},
{"learn":[0.2881324185],"iteration":898,"passed_time":7.761114082,"remaining_time":0.8719382895},
{"learn":[0.2881302244],"iteration":899,"passed_time":7.768617585,"remaining_time":0.8631797317},
{"learn":[0.2881290664],"iteration":900,"passed_time":7.776556133,"remaining_time":0.8544717616},
{"learn":[0.2881033035],"iteration":901,"passed_time":7.784101821,"remaining_time":0.8457228143},
{"learn":[0.2880902044],"iteration":902,"passed_time":7.792675021,"remaining_time":0.837086907},
{"learn":[0.2880866913],"iteration":903,"passed_time":7.800080251,"remaining_time":0.8283271063},
{"learn":[0.2880675626],"iteration":904,"passed_time":7.807873262,"remaining_time":0.8196110054},
{"learn":[0.2880641174],"iteration":905,"passed_time":7.815134981,"remaining_time":0.8108418193},
{"learn":[0.2880221388],"iteration":906,"passed_time":7.822723761,"remaining_time":0.8021094926},
{"learn":[0.2879939979],"iteration":907,"passed_time":7.830363241,"remaining_time":0.7933848218},
{"learn":[0.2879764263],"iteration":908,"passed_time":7.838277155,"remaining_time":0.7846900122},
{"learn":[0.2879689169],"iteration":909,"passed_time":7.846122651,"remaining_time":0.7759901523},
{"learn":[0.2879386977],"iteration":910,"passed_time":7.854180649,"remaining_time":0.7673129284},
{"learn":[0.287928839],"iteration":911,"passed_time":7.862161712,"remaining_time":0.7586296389},
{"learn":[0.2879026057],"iteration":912,"passed_time":7.870008336,"remaining_time":0.7499350769},
{"learn":[0.287865697],"iteration":913,"passed_time":7.878176068,"remaining_time":0.7412725841},
{"learn":[0.287844819],"iteration":914,"passed_time":7.886027597,"remaining_time":0.7325817986},
{"learn":[0.2878226606],"iteration":915,"passed_time":7.893990916,"remaining_time":0.7239030971},
{"learn":[0.2878040322],"iteration":916,"passed_time":7.902293251,"remaining_time":0.715256641},
{"learn":[0.2877861289],"iteration":917,"passed_time":7.910696235,"remaining_time":0.7066199251},
{"learn":[0.2877626201],"iteration":918,"passed_time":7.918274134,"remaining_time":0.6979109955},
{"learn":[0.2877553696],"iteration":919,"passed_time":7.926350677,"remaining_time":0.689247885},
{"learn":[0.2877540345],"iteration":920,"passed_time":7.933886586,"remaining_time":0.6805396746},
{"learn":[0.2877524363],"iteration":921,"passed_time":7.941596026,"remaining_time":0.6718486877},
{"learn":[0.2877460264],"iteration":922,"passed_time":7.949129536,"remaining_time":0.6631451509},
{"learn":[0.2877399612],"iteration":923,"passed_time":7.956875525,"remaining_time":0.6544616232},
{"learn":[0.287715535],"iteration":924,"passed_time":7.965102325,"remaining_time":0.6458191074},
{"learn":[0.2877090481],"iteration":925,"passed_time":7.972615781,"remaining_time":0.6371204836},
{"learn":[0.2876927223],"iteration":926,"passed_time":7.980281817,"remaining_time":0.6284364322},
{"learn":[0.2876909899],"iteration":927,"passed_time":7.987849208,"remaining_time":0.6197469213},
{"learn":[0.2876894523],"iteration":928,"passed_time":7.995402435,"remaining_time":0.6110587437},
{"learn":[0.2876736085],"iteration":929,"passed_time":8.003169414,"remaining_time":0.6023890957},
{"learn":[0.2876484153],"iteration":930,"passed_time":8.010840874,"remaining_time":0.5937143075},
{"learn":[0.2876460926],"iteration":931,"passed_time":8.018402147,"remaining_time":0.585033633},
{"learn":[0.2876386452],"iteration":932,"passed_time":8.02616043,"remaining_time":0.5763695057},
{"learn":[0.2876238885],"iteration":933,"passed_time":8.03378937,"remaining_time":0.5676981782},
{"learn":[0.2876051815],"iteration":934,"passed_time":8.041579181,"remaining_time":0.5590402639},
{"learn":[0.2875991853],"iteration":935,"passed_time":8.049467863,"remaining_time":0.550390965},
{"learn":[0.2875806456],"iteration":936,"passed_time":8.057944955,"remaining_time":0.5417828518},
{"learn":[0.28756931],"iteration":937,"passed_time":8.066874801,"remaining_time":0.5332049442},
{"learn":[0.2875495402],"iteration":938,"passed_time":8.074512728,"remaining_time":0.5245423604},
{"learn":[0.2875244067],"iteration":939,"passed_time":8.082227047,"remaining_time":0.5158868328},
{"learn":[0.2875084314],"iteration":940,"passed_time":8.089832648,"remaining_time":0.5072264891},
{"learn":[0.2874969119],"iteration":941,"passed_time":8.097701093,"remaining_time":0.4985845683},
{"learn":[0.2874930584],"iteration":942,"passed_time":8.105433955,"remaining_time":0.4899360927},
{"learn":[0.2874850829],"iteration":943,"passed_time":8.113411799,"remaining_time":0.4813040898},
{"learn":[0.2874587149],"iteration":944,"passed_time":8.121719836,"remaining_time":0.4726926889},
{"learn":[0.2874337082],"iteration":945,"passed_time":8.12945253,"remaining_time":0.4640490873},
{"learn":[0.2874119459],"iteration":946,"passed_time":8.137199692,"remaining_time":0.4554082193},
{"learn":[0.2873762],"iteration":947,"passed_time":8.145097326,"remaining_time":0.4467774904},
{"learn":[0.2873439922],"iteration":948,"passed_time":8.153021358,"remaining_time":0.4381497252},
{"learn":[0.2873297166],"iteration":949,"passed_time":8.161035169,"remaining_time":0.4295281668},
{"learn":[0.2873223639],"iteration":950,"passed_time":8.169222429,"remaining_time":0.4209168233},
{"learn":[0.2873180811],"iteration":951,"passed_time":8.176850822,"remaining_time":0.4122781927},
{"learn":[0.2872906835],"iteration":952,"passed_time":8.184623829,"remaining_time":0.4036488142},
{"learn":[0.2872796183],"iteration":953,"passed_time":8.19247188,"remaining_time":0.3950248495},
{"learn":[0.2872660099],"iteration":954,"passed_time":8.201622125,"remaining_time":0.3864638697},
{"learn":[0.287233798],"iteration":955,"passed_time":8.211333064,"remaining_time":0.3779274632},
{"learn":[0.2872316616],"iteration":956,"passed_time":8.221996261,"remaining_time":0.369431389},
{"learn":[0.2872110481],"iteration":957,"passed_time":8.230793046,"remaining_time":0.3608489644},
{"learn":[0.2871858867],"iteration":958,"passed_time":8.239789147,"remaining_time":0.3522746142},
{"learn":[0.2871514732],"iteration":959,"passed_time":8.247754514,"remaining_time":0.3436564381},
{"learn":[0.2871458856],"iteration":960,"passed_time":8.255437534,"remaining_time":0.3350281622},
{"learn":[0.2871312639],"iteration":961,"passed_time":8.263341785,"remaining_time":0.3264105902},
{"learn":[0.2871283359],"iteration":962,"passed_time":8.271253703,"remaining_time":0.3177947944},
{"learn":[0.2871158426],"iteration":963,"passed_time":8.279136436,"remaining_time":0.309179369},
{"learn":[0.2870947838],"iteration":964,"passed_time":8.28665625,"remaining_time":0.3005522992},
{"learn":[0.2870837898],"iteration":965,"passed_time":8.294284835,"remaining_time":0.2919313503},
{"learn":[0.2870789973],"iteration":966,"passed_time":8.302253015,"remaining_time":0.2833240429},
{"learn":[0.2870651203],"iteration":967,"passed_time":8.309988579,"remaining_time":0.2747103663},
{"learn":[0.2870427233],"iteration":968,"passed_time":8.318029121,"remaining_time":0.2661082588},
{"learn":[0.2870318134],"iteration":969,"passed_time":8.326031865,"remaining_time":0.2575061402},
{"learn":[0.2870139435],"iteration":970,"passed_time":8.333897005,"remaining_time":0.2489011464},
{"learn":[0.28700254],"iteration":971,"passed_time":8.341571044,"remaining_time":0.24029217},
{"learn":[0.2869814542],"iteration":972,"passed_time":8.349495266,"remaining_time":0.2316920577},
{"learn":[0.2869704201],"iteration":973,"passed_time":8.357680438,"remaining_time":0.2231002992},
{"learn":[0.2869601965],"iteration":974,"passed_time":8.365744093,"remaining_time":0.2145062588},
{"learn":[0.2869523685],"iteration":975,"passed_time":8.373917592,"remaining_time":0.2059160064},
{"learn":[0.2869477703],"iteration":976,"passed_time":8.381847239,"remaining_time":0.1973208664},
{"learn":[0.2869377704],"iteration":977,"passed_time":8.389722674,"remaining_time":0.1887258679},
{"learn":[0.2869213865],"iteration":978,"passed_time":8.397936881,"remaining_time":0.1801396062},
{"learn":[0.2869158947],"iteration":979,"passed_time":8.406026573,"remaining_time":0.1715515627},
{"learn":[0.2869034549],"iteration":980,"passed_time":8.413933828,"remaining_time":0.1629610018},
{"learn":[0.2868920985],"iteration":981,"passed_time":8.42162177,"remaining_time":0.1543678125},
{"learn":[0.2868804867],"iteration":982,"passed_time":8.429277507,"remaining_time":0.1457759081},
{"learn":[0.286879419],"iteration":983,"passed_time":8.436812887,"remaining_time":0.1371839494},
{"learn":[0.2868698756],"iteration":984,"passed_time":8.444672623,"remaining_time":0.1285990755},
{"learn":[0.2868686226],"iteration":985,"passed_time":8.452478587,"remaining_time":0.1200149089},
{"learn":[0.2868644219],"iteration":986,"passed_time":8.460499086,"remaining_time":0.111435145},
{"learn":[0.2868345075],"iteration":987,"passed_time":8.469172845,"remaining_time":0.1028644475},
{"learn":[0.2868244324],"iteration":988,"passed_time":8.476862819,"remaining_time":0.09428259961},
{"learn":[0.2868080327],"iteration":989,"passed_time":8.484459532,"remaining_time":0.08570161143},
{"learn":[0.2867928359],"iteration":990,"passed_time":8.492252022,"remaining_time":0.07712438769},
{"learn":[0.286765605],"iteration":991,"passed_time":8.499968122,"remaining_time":0.06854813002},
{"learn":[0.2867603239],"iteration":992,"passed_time":8.507983151,"remaining_time":0.05997571204},
{"learn":[0.2867408184],"iteration":993,"passed_time":8.515525434,"remaining_time":0.05140156198},
{"learn":[0.2867138794],"iteration":994,"passed_time":8.523541945,"remaining_time":0.04283186907},
{"learn":[0.2867129876],"iteration":995,"passed_time":8.531317491,"remaining_time":0.03426231924},
{"learn":[0.2867011932],"iteration":996,"passed_time":8.539251679,"remaining_time":0.02569483956},
{"learn":[0.2866969823],"iteration":997,"passed_time":8.547095593,"remaining_time":0.01712844808},
{"learn":[0.286672559],"iteration":998,"passed_time":8.555079469,"remaining_time":0.008563643112},
{"learn":[0.2866658061],"iteration":999,"passed_time":8.563115826,"remaining_time":0}
]}